Workbook

Sheet Dashboard
B1: ACQUISITION CALL TRACKER
B2: Home Services Roll-Up | Auto-updates from Companies, Call Log and SMS Nurture
B4: ACTIVITY | E4: PIPELINE BY STAGE | F4: # COS | G4: EBITDA IN STAGE | I4: TEAM ACTIVITY
B5: Target companies in database | C5: =COUNTA(Companies!B2:B1000) -> 906 | E5: 1. Not Contacted | F5: =COUNTIF(Companies!$M$2:$M$1000,E5) -> 906 | G5: =SUMIF(Companies!$M$2:$M$1000,E5,Companies!$F$2:$F$1000) -> 203069000 | I5: Caller | J5: Total Calls | K5: This Week | L5: DM Convos | M5: Meetings Set
B6: Total calls logged | C6: =COUNTA('Call Log'!A2:A5000) -> 0 | E6: 2. In Call Rotation | F6: =COUNTIF(Companies!$M$2:$M$1000,E6) -> 0 | G6: =SUMIF(Companies!$M$2:$M$1000,E6,Companies!$F$2:$F$1000) -> 0 | I6: =Lists!D2 -> Xander | J6: =COUNTIF('Call Log'!$B$2:$B$5000,I6) -> 0 | K6: =COUNTIFS('Call Log'!$B$2:$B$5000,I6,'Call Log'!$A$2:$A$5000,">="&(TODAY()-WEEKDAY(TODAY(),2)+1)) -> 0 | L6: =COUNTIFS('Call Log'!$B$2:$B$5000,I6,'Call Log'!$D$2:$D$5000,"Owner (Decision Maker)") -> 0 | M6: =COUNTIFS('Call Log'!$B$2:$B$5000,I6,'Call Log'!$E$2:$E$5000,"Meeting Set") -> 0
B7: Calls this week (Mon-Sun) | C7: =COUNTIFS('Call Log'!A2:A5000,">="&(TODAY()-WEEKDAY(TODAY(),2)+1)) -> 0 | E7: 3. Meeting Set | F7: =COUNTIF(Companies!$M$2:$M$1000,E7) -> 0 | G7: =SUMIF(Companies!$M$2:$M$1000,E7,Companies!$F$2:$F$1000) -> 0 | I7: =Lists!D3 -> Bram | J7: =COUNTIF('Call Log'!$B$2:$B$5000,I7) -> 0 | K7: =COUNTIFS('Call Log'!$B$2:$B$5000,I7,'Call Log'!$A$2:$A$5000,">="&(TODAY()-WEEKDAY(TODAY(),2)+1)) -> 0 | L7: =COUNTIFS('Call Log'!$B$2:$B$5000,I7,'Call Log'!$D$2:$D$5000,"Owner (Decision Maker)") -> 0 | M7: =COUNTIFS('Call Log'!$B$2:$B$5000,I7,'Call Log'!$E$2:$E$5000,"Meeting Set") -> 0
B8: Owner (DM) reach rate | C8: =IFERROR(COUNTIF('Call Log'!D2:D5000,"Owner (Decision Maker)")/COUNTA('Call Log'!A2:A5000),0) -> 0 | E8: 4. Meeting Held | F8: =COUNTIF(Companies!$M$2:$M$1000,E8) -> 0 | G8: =SUMIF(Companies!$M$2:$M$1000,E8,Companies!$F$2:$F$1000) -> 0 | I8: =Lists!D4 -> Andrew | J8: =COUNTIF('Call Log'!$B$2:$B$5000,I8) -> 0 | K8: =COUNTIFS('Call Log'!$B$2:$B$5000,I8,'Call Log'!$A$2:$A$5000,">="&(TODAY()-WEEKDAY(TODAY(),2)+1)) -> 0 | L8: =COUNTIFS('Call Log'!$B$2:$B$5000,I8,'Call Log'!$D$2:$D$5000,"Owner (Decision Maker)") -> 0 | M8: =COUNTIFS('Call Log'!$B$2:$B$5000,I8,'Call Log'!$E$2:$E$5000,"Meeting Set") -> 0
B9: Meetings set (in pipeline now) | C9: =COUNTIF(Companies!M2:M1000,"3. Meeting Set") -> 0 | E9: 5. NDA Signed | F9: =COUNTIF(Companies!$M$2:$M$1000,E9) -> 0 | G9: =SUMIF(Companies!$M$2:$M$1000,E9,Companies!$F$2:$F$1000) -> 0 | I9: =Lists!D5 -> Davis | J9: =COUNTIF('Call Log'!$B$2:$B$5000,I9) -> 0 | K9: =COUNTIFS('Call Log'!$B$2:$B$5000,I9,'Call Log'!$A$2:$A$5000,">="&(TODAY()-WEEKDAY(TODAY(),2)+1)) -> 0 | L9: =COUNTIFS('Call Log'!$B$2:$B$5000,I9,'Call Log'!$D$2:$D$5000,"Owner (Decision Maker)") -> 0 | M9: =COUNTIFS('Call Log'!$B$2:$B$5000,I9,'Call Log'!$E$2:$E$5000,"Meeting Set") -> 0
B10: Upcoming meetings on calendar | C10: =COUNTIF(Companies!U2:U1000,">="&TODAY()) -> 0 | E10: 6. Financials Received | F10: =COUNTIF(Companies!$M$2:$M$1000,E10) -> 0 | G10: =SUMIF(Companies!$M$2:$M$1000,E10,Companies!$F$2:$F$1000) -> 0 | I10: =Lists!D6 -> TJ | J10: =COUNTIF('Call Log'!$B$2:$B$5000,I10) -> 0 | K10: =COUNTIFS('Call Log'!$B$2:$B$5000,I10,'Call Log'!$A$2:$A$5000,">="&(TODAY()-WEEKDAY(TODAY(),2)+1)) -> 0 | L10: =COUNTIFS('Call Log'!$B$2:$B$5000,I10,'Call Log'!$D$2:$D$5000,"Owner (Decision Maker)") -> 0 | M10: =COUNTIFS('Call Log'!$B$2:$B$5000,I10,'Call Log'!$E$2:$E$5000,"Meeting Set") -> 0
B11: Follow-ups OVERDUE | C11: =COUNTIF(Companies!T2:T1000,"<"&TODAY()) -> 0 | E11: 7. LOI Submitted | F11: =COUNTIF(Companies!$M$2:$M$1000,E11) -> 0 | G11: =SUMIF(Companies!$M$2:$M$1000,E11,Companies!$F$2:$F$1000) -> 0
B12: Follow-ups due today | C12: =COUNTIF(Companies!T2:T1000,TODAY()) -> 0 | E12: 8. Diligence | F12: =COUNTIF(Companies!$M$2:$M$1000,E12) -> 0 | G12: =SUMIF(Companies!$M$2:$M$1000,E12,Companies!$F$2:$F$1000) -> 0
B13: In rotation, ZERO calls this wk | C13: =COUNTIFS(Companies!M2:M1000,"2. In Call Rotation",Companies!P2:P1000,0) -> 0 | E13: 9. Closed - Acquired | F13: =COUNTIF(Companies!$M$2:$M$1000,E13) -> 0 | G13: =SUMIF(Companies!$M$2:$M$1000,E13,Companies!$F$2:$F$1000) -> 0 | I13: DAILY ROUTINE
B14: On SMS nurture list | C14: =COUNTA('SMS Nurture'!A2:A500) -> 0 | E14: X. SMS Nurture (Said No) | F14: =COUNTIF(Companies!$M$2:$M$1000,E14) -> 0 | G14: =SUMIF(Companies!$M$2:$M$1000,E14,Companies!$F$2:$F$1000) -> 0 | I14: 1. Clear anything RED (overdue follow-ups on Companies).
B15: Texts due to send now | C15: =COUNTIFS('SMS Nurture'!G2:G500,"<="&TODAY(),'SMS Nurture'!H2:H500,"<>OPTED OUT - never text again") -> 0 | I15: 2. Check 'In rotation, ZERO calls this wk' - orange rows on Companies need a dial today.
B16: Hot targets | C16: =COUNTIF(Companies!N2:N1000,"Hot") -> 0 | I16: 3. Send any SMS due (yellow rows on SMS Nurture tab).
E17: BY TRADE | F17: # COS | I17: 4. Log every dial in Call Log the moment it ends - even no-answers.
E18: HVAC | F18: =COUNTIF(Companies!$H$2:$H$1000,E18) -> 469
E19: Plumbing | F19: =COUNTIF(Companies!$H$2:$H$1000,E19) -> 393
E20: Electrical | F20: =COUNTIF(Companies!$H$2:$H$1000,E20) -> 0
E21: HVAC + Plumbing | F21: =COUNTIF(Companies!$H$2:$H$1000,E21) -> 44
E22: Multi-Trade | F22: =COUNTIF(Companies!$H$2:$H$1000,E22) -> 0

Sheet Lists
A1: Stage | B1: Trade | C1: Interest | D1: Caller | E1: Reached | F1: Call Outcome | G1: Lead Source | H1: SMS Status
A2: 1. Not Contacted | B2: HVAC | C2: Hot | D2: Xander | E2: Owner (Decision Maker) | F2: Meeting Set | G2: Google Maps scrape | H2: No reply yet
A3: 2. In Call Rotation | B3: Plumbing | C3: Warm | D3: Bram | E3: Voicemail | F3: Meaningful Conversation | G3: Purchased list | H3: Replied - still no
A4: 3. Meeting Set | B4: Electrical | C4: Lukewarm | D4: Andrew | E4: No Answer | F4: Callback Scheduled | G4: Referral | H4: Replied - INTERESTED
A5: 4. Meeting Held | B5: HVAC + Plumbing | C5: Cold | D5: Davis | E5: Gatekeeper | F5: Left Voicemail | G5: BizBuySell | H5: OPTED OUT - never text again
A6: 5. NDA Signed | B6: Multi-Trade | C6: Said No | D6: TJ | E6: Wrong Number | F6: No Answer | G6: Broker
A7: 6. Financials Received | C7: Unknown | F7: Not Interested - move to SMS List | G7: Trade association
A8: 7. LOI Submitted | F8: Bad Number | G8: Other
A9: 8. Diligence | D9: <- Your team; edit here if the roster changes | F9: Do Not Contact (asked us to stop)
A10: 9. Closed - Acquired
A11: X. SMS Nurture (Said No)

Sheet Companies
A1: ID | B1: Company Name | C1: Owner Name | D1: Owner Cell | E1: Employees | F1: EBITDA / SDE ($) | G1: Est. Revenue ($) | H1: Trade | I1: City | J1: State | K1: Office Phone | L1: Email | M1: Stage | N1: Interest | O1: Last Caller | P1: Calls This Wk | Q1: Total Calls | R1: Last Call | S1: Next Caller | T1: Next Action Date | U1: Meeting Date | V1: Meeting Time & Place | W1: Asking Price ($) | X1: Trucks | Y1: Owner Age / Motivation | Z1: Lead Source | AA1: Notes
A2: C001 | B2: Geary Pacific Supply | C2: Russ Geary | D2: (916) 716-6726 | E2: 250 | F2: 8019000 | G2: 66825000 | H2: HVAC | I2: Kingman | J2: AZ | K2: (928) 718-7177 | L2: russ@gearypacific.com | M2: 1. Not Contacted | N2: Unknown | O2: =IF(B2="","",IFERROR(LOOKUP(2,1/('Call Log'!$C$2:$C$5000=B2),'Call Log'!$B$2:$B$5000),"")) | P2: =IF(B2="","",COUNTIFS('Call Log'!$C$2:$C$5000,B2,'Call Log'!$A$2:$A$5000,">="&(TODAY()-WEEKDAY(TODAY(),2)+1))) -> 0 | Q2: =IF(B2="","",COUNTIF('Call Log'!$C$2:$C$5000,B2)) -> 0 | R2: =IF(B2="","",IFERROR(IF(MAXIFS('Call Log'!$A$2:$A$5000,'Call Log'!$C$2:$C$5000,B2)=0,"",MAXIFS('Call Log'!$A$2:$A$5000,'Call Log'!$C$2:$C$5000,B2)),"")) | AA2: Contact title 'Regional V.P.' - verify decision maker | Owner found via Apollo | EBITDA = 12% revenue proxy
A3: C002 | B3: Any Hour Services - Electric, Plumbing, Heating & Air | C3: Angedet Thomas | D3: (757) 337-4204 | E3: 260 | F3: 5208000 | G3: 43400000 | H3: HVAC + Plumbing | I3: Phoenix | J3: AZ | K3: (602) 609-7184 | M3: 1. Not Contacted | N3: Unknown | O3: =IF(B3="","",IFERROR(LOOKUP(2,1/('Call Log'!$C$2:$C$5000=B3),'Call Log'!$B$2:$B$5000),"")) | P3: =IF(B3="","",COUNTIFS('Call Log'!$C$2:$C$5000,B3,'Call Log'!$A$2:$A$5000,">="&(TODAY()-WEEKDAY(TODAY(),2)+1))) -> 0 | Q3: =IF(B3="","",COUNTIF('Call Log'!$C$2:$C$5000,B3)) -> 0 | R3: =IF(B3="","",IFERROR(IF(MAXIFS('Call Log'!$A$2:$A$5000,'Call Log'!$C$2:$C$5000,B3)=0,"",MAXIFS('Call Log'!$A$2:$A$5000,'Call Log'!$C$2:$C$5000,B3)),"")) | AA3: Owner found via Apollo | EBITDA = 12% revenue proxy
A4: C003 | B4: Area Plumbing | C4: Jason Griffin | D4: (928) 388-5459 | E4: 5 | F4: 5013000 | G4: 41775000 | H4: Plumbing | I4: Yuma | J4: AZ | K4: (928) 344-0868 | L4: jason@areaplumbing.com | M4: 1. Not Contacted | N4: Unknown | O4: =IF(B4="","",IFERROR(LOOKUP(2,1/('Call Log'!$C$2:$C$5000=B4),'Call Log'!$B$2:$B$5000),"")) | P4: =IF(B4="","",COUNTIFS('Call Log'!$C$2:$C$5000,B4,'Call Log'!$A$2:$A$5000,">="&(TODAY()-WEEKDAY(TODAY(),2)+1))) -> 0 | Q4: =IF(B4="","",COUNTIF('Call Log'!$C$2:$C$5000,B4)) -> 0 | R4: =IF(B4="","",IFERROR(IF(MAXIFS('Call Log'!$A$2:$A$5000,'Call Log'!$C$2:$C$5000,B4)=0,"",MAXIFS('Call Log'!$A$2:$A$5000,'Call Log'!$C$2:$C$5000,B4)),"")) | Z4: roc-posting-list | AA4: Contact title 'General Manager' - verify decision maker | ROC 105658 R-37 | EBITDA = 12% revenue proxy | Size est. midpoint - ZoomInfo: 1-10 employees
A5: C004 | B5: TDK Comfort Systems Inc | C5: Troy Douglas Koski | D5: (928) 237-6050 | E5: 5 | F5: 3897000 | G5: 32476000 | H5: HVAC | I5: Chino Valley | J5: AZ | K5: (928) 636-0846 | L5: troy@tdkcomfortsystems.com | M5: 1. Not Contacted | N5: Unknown | O5: =IF(B5="","",IFERROR(LOOKUP(2,1/('Call Log'!$C$2:$C$5000=B5),'Call Log'!$B$2:$B$5000),"")) | P5: =IF(B5="","",COUNTIFS('Call Log'!$C$2:$C$5000,B5,'Call Log'!$A$2:$A$5000,">="&(TODAY()-WEEKDAY(TODAY(),2)+1))) -> 0 | Q5: =IF(B5="","",COUNTIF('Call Log'!$C$2:$C$5000,B5)) -> 0 | R5: =IF(B5="","",IFERROR(IF(MAXIFS('Call Log'!$A$2:$A$5000,'Call Log'!$C$2:$C$5000,B5)=0,"",MAXIFS('Call Log'!$A$2:$A$5000,'Call Log'!$C$2:$C$5000,B5)),"")) | Z5: roc-posting-list | AA5: ROC 154061 CR-39 | EBITDA = 12% revenue proxy
A6: C005 | B6: Hamstra Heating & Cooling | C6: Wade Hamstra | D6: (520) 250-1796 | E6: 35 | F6: 3667000 | G6: 30559000 | H6: HVAC | I6: Tucson | J6: AZ | K6: (520) 629-9833 | L6: whamstra@hamstraac.com | M6: 1. Not Contacted | N6: Unknown | O6: =IF(B6="","",IFERROR(LOOKUP(2,1/('Call Log'!$C$2:$C$5000=B6),'Call Log'!$B$2:$B$5000),"")) | P6: =IF(B6="","",COUNTIFS('Call Log'!$C$2:$C$5000,B6,'Call Log'!$A$2:$A$5000,">="&(TODAY()-WEEKDAY(TODAY(),2)+1))) -> 0 | Q6: =IF(B6="","",COUNTIF('Call Log'!$C$2:$C$5000,B6)) -> 0 | R6: =IF(B6="","",IFERROR(IF(MAXIFS('Call Log'!$A$2:$A$5000,'Call Log'!$C$2:$C$5000,B6)=0,"",MAXIFS('Call Log'!$A$2:$A$5000,'Call Log'!$C$2:$C$5000,B6)),"")) | AA6: Contact title 'Owner, Vice President' - verify decision maker | Owner found via Apollo | ROC 59073 R-39R | EBITDA = 12% revenue proxy
A7: C006 | B7: Wolfgangs Cooling, Heating & Plumbing | C7: Tom Doll | D7: (480) 529-9926 | E7: 25 | F7: 3329000 | G7: 27745000 | H7: HVAC | I7: Tempe | J7: AZ | K7: (928) 228-5968 | M7: 1. Not Contacted | N7: Unknown | O7: =IF(B7="","",IFERROR(LOOKUP(2,1/('Call Log'!$C$2:$C$5000=B7),'Call Log'!$B$2:$B$5000),"")) | P7: =IF(B7="","",COUNTIFS('Call Log'!$C$2:$C$5000,B7,'Call Log'!$A$2:$A$5000,">="&(TODAY()-WEEKDAY(TODAY(),2)+1))) -> 0 | Q7: =IF(B7="","",COUNTIF('Call Log'!$C$2:$C$5000,B7)) -> 0 | R7: =IF(B7="","",IFERROR(IF(MAXIFS('Call Log'!$A$2:$A$5000,'Call Log'!$C$2:$C$5000,B7)=0,"",MAXIFS('Call Log'!$A$2:$A$5000,'Call Log'!$C$2:$C$5000,B7)),"")) | AA7: Contact title 'President' - verify decision maker | Other locations: Prescott Valley | Owner found via Apollo | EBITDA = 12% revenue proxy
A8: C007 | B8: Chandler Air | C8: Ryan Bond | D8: (602) 684-0267 | E8: 30 | F8: 3142000 | G8: 26185000 | H8: HVAC | I8: Chandler | J8: AZ | K8: (480) 372-5008 | M8: 1. Not Contacted | N8: Unknown | O8: =IF(B8="","",IFERROR(LOOKUP(2,1/('Call Log'!$C$2:$C$5000=B8),'Call Log'!$B$2:$B$5000),"")) | P8: =IF(B8="","",COUNTIFS('Call Log'!$C$2:$C$5000,B8,'Call Log'!$A$2:$A$5000,">="&(TODAY()-WEEKDAY(TODAY(),2)+1))) -> 0 | Q8: =IF(B8="","",COUNTIF('Call Log'!$C$2:$C$5000,B8)) -> 0 | R8: =IF(B8="","",IFERROR(IF(MAXIFS('Call Log'!$A$2:$A$5000,'Call Log'!$C$2:$C$5000,B8)=0,"",MAXIFS('Call Log'!$A$2:$A$5000,'Call Log'!$C$2:$C$5000,B8)),"")) | Z8: roc-posting-list | AA8: Contact title 'Owner and Principal' - verify decision maker | ROC 220890 C-39 | EBITDA = 12% revenue proxy | Size est. midpoint - ZoomInfo: 11-50 employees
A9: C008 | B9: Mason Pro Services | C9: Paden James Mason | D9: (480) 797-4839 | E9: 30 | F9: 2970000 | G9: 24747000 | H9: HVAC | I9: Chandler | J9: AZ | K9: (480) 835-9928 | L9: paden@masonproservices.com | M9: 1. Not Contacted | N9: Unknown | O9: =IF(B9="","",IFERROR(LOOKUP(2,1/('Call Log'!$C$2:$C$5000=B9),'Call Log'!$B$2:$B$5000),"")) | P9: =IF(B9="","",COUNTIFS('Call Log'!$C$2:$C$5000,B9,'Call Log'!$A$2:$A$5000,">="&(TODAY()-WEEKDAY(TODAY(),2)+1))) -> 0 | Q9: =IF(B9="","",COUNTIF('Call Log'!$C$2:$C$5000,B9)) -> 0 | R9: =IF(B9="","",IFERROR(IF(MAXIFS('Call Log'!$A$2:$A$5000,'Call Log'!$C$2:$C$5000,B9)=0,"",MAXIFS('Call Log'!$A$2:$A$5000,'Call Log'!$C$2:$C$5000,B9)),"")) | Z9: roc-posting-list | AA9: Contact title 'Service Administrator' - verify decision maker | ROC 331897 CR-37 | EBITDA = 12% revenue proxy
A10: C009 | B10: Superstition Plumbing | C10: Roy Glenn Jorgenson | D10: (801) 678-2030 | E10: 3 | F10: 2854000 | G10: 23785000 | H10: Plumbing | I10: Mesa | J10: AZ | K10: (480) 833-3112 | L10: roy@superstitionplumbing.com | M10: 1. Not Contacted | N10: Unknown | O10: =IF(B10="","",IFERROR(LOOKUP(2,1/('Call Log'!$C$2:$C$5000=B10),'Call Log'!$B$2:$B$5000),"")) | P10: =IF(B10="","",COUNTIFS('Call Log'!$C$2:$C$5000,B10,'Call Log'!$A$2:$A$5000,">="&(TODAY()-WEEKDAY(TODAY(),2)+1))) -> 0 | Q10: =IF(B10="","",COUNTIF('Call Log'!$C$2:$C$5000,B10)) -> 0 | R10: =IF(B10="","",IFERROR(IF(MAXIFS('Call Log'!$A$2:$A$5000,'Call Log'!$C$2:$C$5000,B10)=0,"",MAXIFS('Call Log'!$A$2:$A$5000,'Call Log'!$C$2:$C$5000,B10)),"")) | Z10: roc-apify | AA10: ROC 361375 | EBITDA = 12% revenue proxy
A11: C010 | B11: Plumbing Masters | C11: Brian Joe McQuistion | D11: (602) 377-6931 | E11: 29 | F11: 2798000 | G11: 23317000 | H11: Plumbing | I11: Peoria | J11: AZ | K11: (602) 637-0315 | L11: plumbingmasters9299bm@myplumberaz.com | M11: 1. Not Contacted | N11: Unknown | O11: =IF(B11="","",IFERROR(LOOKUP(2,1/('Call Log'!$C$2:$C$5000=B11),'Call Log'!$B$2:$B$5000),"")) | P11: =IF(B11="","",COUNTIFS('Call Log'!$C$2:$C$5000,B11,'Call Log'!$A$2:$A$5000,">="&(TODAY()-WEEKDAY(TODAY(),2)+1))) -> 0 | Q11: =IF(B11="","",COUNTIF('Call Log'!$C$2:$C$5000,B11)) -> 0 | R11: =IF(B11="","",IFERROR(IF(MAXIFS('Call Log'!$A$2:$A$5000,'Call Log'!$C$2:$C$5000,B11)=0,"",MAXIFS('Call Log'!$A$2:$A$5000,'Call Log'!$C$2:$C$5000,B11)),"")) | Z11: roc-apify | AA11: Other locations: Mesa | ROC 255233 | EBITDA = 12% revenue proxy
A12: C011 | B12: Hendel's Air Conditioning Inc. | C12: Robert Jason Hendel | D12: (631) 804-7361 | E12: 8 | F12: 2743000 | G12: 22861000 | H12: HVAC | I12: Chandler | J12: AZ | K12: (480) 813-1700 | M12: 1. Not Contacted | N12: Unknown | O12: =IF(B12="","",IFERROR(LOOKUP(2,1/('Call Log'!$C$2:$C$5000=B12),'Call Log'!$B$2:$B$5000),"")) | P12: =IF(B12="","",COUNTIFS('Call Log'!$C$2:$C$5000,B12,'Call Log'!$A$2:$A$5000,">="&(TODAY()-WEEKDAY(TODAY(),2)+1))) -> 0 | Q12: =IF(B12="","",COUNTIF('Call Log'!$C$2:$C$5000,B12)) -> 0 | R12: =IF(B12="","",IFERROR(IF(MAXIFS('Call Log'!$A$2:$A$5000,'Call Log'!$C$2:$C$5000,B12)=0,"",MAXIFS('Call Log'!$A$2:$A$5000,'Call Log'!$C$2:$C$5000,B12)),"")) | Z12: roc-posting-list | AA12: Co-owners: Julia Hendel | Contact title 'General Manager' - verify decision maker | ROC 50612 R-39R | EBITDA = 12% revenue proxy
A13: C012 | B13: Rim Country Mechanical Inc | C13: Corey Lunt | D13: (928) 242-1660 | E13: 9 | F13: 2522000 | G13: 21014000 | H13: HVAC | I13: Show Low | J13: AZ | K13: (928) 537-1803 | L13: coreylunt@rimcountrymechanical.com | M13: 1. Not Contacted | N13: Unknown | O13: =IF(B13="","",IFERROR(LOOKUP(2,1/('Call Log'!$C$2:$C$5000=B13),'Call Log'!$B$2:$B$5000),"")) | P13: =IF(B13="","",COUNTIFS('Call Log'!$C$2:$C$5000,B13,'Call Log'!$A$2:$A$5000,">="&(TODAY()-WEEKDAY(TODAY(),2)+1))) -> 0 | Q13: =IF(B13="","",COUNTIF('Call Log'!$C$2:$C$5000,B13)) -> 0 | R13: =IF(B13="","",IFERROR(IF(MAXIFS('Call Log'!$A$2:$A$5000,'Call Log'!$C$2:$C$5000,B13)=0,"",MAXIFS('Call Log'!$A$2:$A$5000,'Call Log'!$C$2:$C$5000,B13)),"")) | Z13: roc-posting-list | AA13: ROC 285833 CR-79 | EBITDA = 12% revenue proxy
A14: C013 | B14: Sav-On Plumbing | C14: Paul Johnson | D14: (619) 823-7851 | E14: 4 | F14: 2508000 | G14: 20904000 | H14: Plumbing | I14: Glendale | J14: AZ | K14: (623) 487-9500 | L14: paul@sav-onplumbing.com | M14: 1. Not Contacted | N14: Unknown | O14: =IF(B14="","",IFERROR(LOOKUP(2,1/('Call Log'!$C$2:$C$5000=B14),'Call Log'!$B$2:$B$5000),"")) | P14: =IF(B14="","",COUNTIFS('Call Log'!$C$2:$C$5000,B14,'Call Log'!$A$2:$A$5000,">="&(TODAY()-WEEKDAY(TODAY(),2)+1))) -> 0 | Q14: =IF(B14="","",COUNTIF('Call Log'!$C$2:$C$5000,B14)) -> 0 | R14: =IF(B14="","",IFERROR(IF(MAXIFS('Call Log'!$A$2:$A$5000,'Call Log'!$C$2:$C$5000,B14)=0,"",MAXIFS('Call Log'!$A$2:$A$5000,'Call Log'!$C$2:$C$5000,B14)),"")) | AA14: Owner found via Apollo | EBITDA = 12% revenue proxy
A15: C014 | B15: ACE Home Services (formerly Yavapai Plumbing & Heating) | C15: Jay Hazlewood | D15: (480) 717-9339 | E15: 110 | F15: 2400000 | G15: 20000000 | H15: HVAC + Plumbing | I15: Prescott | J15: AZ | K15: (928) 683-7898 | M15: 1. Not Contacted | N15: Unknown | O15: =IF(B15="","",IFERROR(LOOKUP(2,1/('Call Log'!$C$2:$C$5000=B15),'Call Log'!$B$2:$B$5000),"")) | P15: =IF(B15="","",COUNTIFS('Call Log'!$C$2:$C$5000,B15,'Call Log'!$A$2:$A$5000,">="&(TODAY()-WEEKDAY(TODAY(),2)+1))) -> 0 | Q15: =IF(B15="","",COUNTIF('Call Log'!$C$2:$C$5000,B15)) -> 0 | R15: =IF(B15="","",IFERROR(IF(MAXIFS('Call Log'!$A$2:$A$5000,'Call Log'!$C$2:$C$5000,B15)=0,"",MAXIFS('Call Log'!$A$2:$A$5000,'Call Log'!$C$2:$C$5000,B15)),"")) | AA15: Contact title 'Owner' - verify decision maker | Owner found via Apollo | EBITDA = 12% revenue proxy
A16: C015 | B16: ACE Home Services (formerly AZ Best Plumbing) | C16: Jay Hazlewood | D16: (480) 717-9339 | E16: 110 | F16: 2400000 | G16: 20000000 | H16: HVAC + Plumbing | I16: Sedona | J16: AZ | K16: (928) 224-1764 | M16: 1. Not Contacted | N16: Unknown | O16: =IF(B16="","",IFERROR(LOOKUP(2,1/('Call Log'!$C$2:$C$5000=B16),'Call Log'!$B$2:$B$5000),"")) | P16: =IF(B16="","",COUNTIFS('Call Log'!$C$2:$C$5000,B16,'Call Log'!$A$2:$A$5000,">="&(TODAY()-WEEKDAY(TODAY(),2)+1))) -> 0 | Q16: =IF(B16="","",COUNTIF('Call Log'!$C$2:$C$5000,B16)) -> 0 | R16: =IF(B16="","",IFERROR(IF(MAXIFS('Call Log'!$A$2:$A$5000,'Call Log'!$C$2:$C$5000,B16)=0,"",MAXIFS('Call Log'!$A$2:$A$5000,'Call Log'!$C$2:$C$5000,B16)),"")) | AA16: Contact title 'Owner' - verify decision maker | Owner found via Apollo | EBITDA = 12% revenue proxy
A17: C016 | B17: Benefit Air Conditioning | C17: Michael Sean Elia | D17: (602) 293-6293 | E17: 8 | F17: 2393000 | G17: 19943000 | H17: HVAC | I17: Phoenix | J17: AZ | K17: (602) 840-9229 | L17: mike@benefitair.com | M17: 1. Not Contacted | N17: Unknown | O17: =IF(B17="","",IFERROR(LOOKUP(2,1/('Call Log'!$C$2:$C$5000=B17),'Call Log'!$B$2:$B$5000),"")) | P17: =IF(B17="","",COUNTIFS('Call Log'!$C$2:$C$5000,B17,'Call Log'!$A$2:$A$5000,">="&(TODAY()-WEEKDAY(TODAY(),2)+1))) -> 0 | Q17: =IF(B17="","",COUNTIF('Call Log'!$C$2:$C$5000,B17)) -> 0 | R17: =IF(B17="","",IFERROR(IF(MAXIFS('Call Log'!$A$2:$A$5000,'Call Log'!$C$2:$C$5000,B17)=0,"",MAXIFS('Call Log'!$A$2:$A$5000,'Call Log'!$C$2:$C$5000,B17)),"")) | Z17: roc-apify | AA17: ROC 173187 | EBITDA = 12% revenue proxy
A18: C017 | B18: Intermountain Plumbing & Mechanical | C18: David Allen Pulley | D18: (928) 220-1361 | E18: 9 | F18: 2296000 | G18: 19132000 | H18: Plumbing | I18: Flagstaff | J18: AZ | K18: (928) 526-7006 | L18: dave@intermountainaz.com | M18: 1. Not Contacted | N18: Unknown | O18: =IF(B18="","",IFERROR(LOOKUP(2,1/('Call Log'!$C$2:$C$5000=B18),'Call Log'!$B$2:$B$5000),"")) | P18: =IF(B18="","",COUNTIFS('Call Log'!$C$2:$C$5000,B18,'Call Log'!$A$2:$A$5000,">="&(TODAY()-WEEKDAY(TODAY(),2)+1))) -> 0 | Q18: =IF(B18="","",COUNTIF('Call Log'!$C$2:$C$5000,B18)) -> 0 | R18: =IF(B18="","",IFERROR(IF(MAXIFS('Call Log'!$A$2:$A$5000,'Call Log'!$C$2:$C$5000,B18)=0,"",MAXIFS('Call Log'!$A$2:$A$5000,'Call Log'!$C$2:$C$5000,B18)),"")) | Z18: roc-posting-list | AA18: Contact title 'General Manager' - verify decision maker | ROC 91860 R-37R | EBITDA = 12% revenue proxy
A19: C018 | B19: Comfort Pro Heating & Cooling, Inc. | C19: Robert Uwe Kunzmann | D19: (928) 927-9000 | E19: 6 | F19: 2169000 | G19: 18079000 | H19: HVAC | I19: Prescott | J19: AZ | K19: (928) 899-4250 | L19: robkunzmann@prorvandair.com | M19: 1. Not Contacted | N19: Unknown | O19: =IF(B19="","",IFERROR(LOOKUP(2,1/('Call Log'!$C$2:$C$5000=B19),'Call Log'!$B$2:$B$5000),"")) | P19: =IF(B19="","",COUNTIFS('Call Log'!$C$2:$C$5000,B19,'Call Log'!$A$2:$A$5000,">="&(TODAY()-WEEKDAY(TODAY(),2)+1))) -> 0 | Q19: =IF(B19="","",COUNTIF('Call Log'!$C$2:$C$5000,B19)) -> 0 | R19: =IF(B19="","",IFERROR(IF(MAXIFS('Call Log'!$A$2:$A$5000,'Call Log'!$C$2:$C$5000,B19)=0,"",MAXIFS('Call Log'!$A$2:$A$5000,'Call Log'!$C$2:$C$5000,B19)),"")) | Z19: roc-posting-list | AA19: ROC 241514 R-39R | EBITDA = 12% revenue proxy
A20: C019 | B20: Efficiency Heating & Cooling LLC | C20: Drew Nicholas | D20: (602) 919-4054 | E20: 20 | F20: 1830000 | G20: 15247000 | H20: HVAC | I20: Gilbert | J20: AZ | K20: (480) 331-8904 | L20: drew@effmech.com | M20: 1. Not Contacted | N20: Unknown | O20: =IF(B20="","",IFERROR(LOOKUP(2,1/('Call Log'!$C$2:$C$5000=B20),'Call Log'!$B$2:$B$5000),"")) | P20: =IF(B20="","",COUNTIFS('Call Log'!$C$2:$C$5000,B20,'Call Log'!$A$2:$A$5000,">="&(TODAY()-WEEKDAY(TODAY(),2)+1))) -> 0 | Q20: =IF(B20="","",COUNTIF('Call Log'!$C$2:$C$5000,B20)) -> 0 | R20: =IF(B20="","",IFERROR(IF(MAXIFS('Call Log'!$A$2:$A$5000,'Call Log'!$C$2:$C$5000,B20)=0,"",MAXIFS('Call Log'!$A$2:$A$5000,'Call Log'!$C$2:$C$5000,B20)),"")) | Z20: roc-posting-list | AA20: Contact title 'Project Manager' - verify decision maker | ROC 319039 CR-39 | EBITDA = 12% revenue proxy
A21: C020 | B21: Cool Blew Inc. | C21: Robert Leon Proctor | D21: (602) 292-3707 | E21: 11 | F21: 1740000 | G21: 14500000 | H21: HVAC | I21: Peoria | J21: AZ | K21: (623) 872-2900 | M21: 1. Not Contacted | N21: Unknown | O21: =IF(B21="","",IFERROR(LOOKUP(2,1/('Call Log'!$C$2:$C$5000=B21),'Call Log'!$B$2:$B$5000),"")) | P21: =IF(B21="","",COUNTIFS('Call Log'!$C$2:$C$5000,B21,'Call Log'!$A$2:$A$5000,">="&(TODAY()-WEEKDAY(TODAY(),2)+1))) -> 0 | Q21: =IF(B21="","",COUNTIF('Call Log'!$C$2:$C$5000,B21)) -> 0 | R21: =IF(B21="","",IFERROR(IF(MAXIFS('Call Log'!$A$2:$A$5000,'Call Log'!$C$2:$C$5000,B21)=0,"",MAXIFS('Call Log'!$A$2:$A$5000,'Call Log'!$C$2:$C$5000,B21)),"")) | Z21: roc-posting-list | AA21: Other locations: Surprise | ROC 176357 CR-39 | EBITDA = 12% revenue proxy
A22: C021 | B22: EZ Flow Plumbing, LLC | C22: Scott William Reisack | D22: (480) 340-0752 | E22: 6 | F22: 1334000 | G22: 11120000 | H22: Plumbing | I22: Chandler | J22: AZ | K22: (602) 613-4525 | L22: scott@ezflowplumbingaz.com | M22: 1. Not Contacted | N22: Unknown | O22: =IF(B22="","",IFERROR(LOOKUP(2,1/('Call Log'!$C$2:$C$5000=B22),'Call Log'!$B$2:$B$5000),"")) | P22: =IF(B22="","",COUNTIFS('Call Log'!$C$2:$C$5000,B22,'Call Log'!$A$2:$A$5000,">="&(TODAY()-WEEKDAY(TODAY(),2)+1))) -> 0 | Q22: =IF(B22="","",COUNTIF('Call Log'!$C$2:$C$5000,B22)) -> 0 | R22: =IF(B22="","",IFERROR(IF(MAXIFS('Call Log'!$A$2:$A$5000,'Call Log'!$C$2:$C$5000,B22)=0,"",MAXIFS('Call Log'!$A$2:$A$5000,'Call Log'!$C$2:$C$5000,B22)),"")) | Z22: roc-posting-list | AA22: Other locations: Tempe | ROC 242432 CR-37 | EBITDA = 12% revenue proxy
A23: C022 | B23: SMW Refrigeration and Heating, LLC | C23: Scott Michael Wetter | D23: (480) 462-6650 | E23: 12 | F23: 1178000 | G23: 9817000 | H23: HVAC | I23: Tempe | J23: AZ | K23: (855) 875-2665 | L23: scott@smwrefrigeration.com | M23: 1. Not Contacted | N23: Unknown | O23: =IF(B23="","",IFERROR(LOOKUP(2,1/('Call Log'!$C$2:$C$5000=B23),'Call Log'!$B$2:$B$5000),"")) | P23: =IF(B23="","",COUNTIFS('Call Log'!$C$2:$C$5000,B23,'Call Log'!$A$2:$A$5000,">="&(TODAY()-WEEKDAY(TODAY(),2)+1))) -> 0 | Q23: =IF(B23="","",COUNTIF('Call Log'!$C$2:$C$5000,B23)) -> 0 | R23: =IF(B23="","",IFERROR(IF(MAXIFS('Call Log'!$A$2:$A$5000,'Call Log'!$C$2:$C$5000,B23)=0,"",MAXIFS('Call Log'!$A$2:$A$5000,'Call Log'!$C$2:$C$5000,B23)),"")) | Z23: roc-posting-list | AA23: ROC 172364 R-39R | EBITDA = 12% revenue proxy
A24: C023 | B24: Curtis Plumbing | C24: Jonathan Curtis | D24: (813) 951-3459 | E24: 8 | F24: 1167000 | G24: 9721000 | H24: Plumbing | I24: Tucson | J24: AZ | K24: (520) 323-7697 | M24: 1. Not Contacted | N24: Unknown | O24: =IF(B24="","",IFERROR(LOOKUP(2,1/('Call Log'!$C$2:$C$5000=B24),'Call Log'!$B$2:$B$5000),"")) | P24: =IF(B24="","",COUNTIFS('Call Log'!$C$2:$C$5000,B24,'Call Log'!$A$2:$A$5000,">="&(TODAY()-WEEKDAY(TODAY(),2)+1))) -> 0 | Q24: =IF(B24="","",COUNTIF('Call Log'!$C$2:$C$5000,B24)) -> 0 | R24: =IF(B24="","",IFERROR(IF(MAXIFS('Call Log'!$A$2:$A$5000,'Call Log'!$C$2:$C$5000,B24)=0,"",MAXIFS('Call Log'!$A$2:$A$5000,'Call Log'!$C$2:$C$5000,B24)),"")) | AA24: Owner found via Apollo | ROC 61230 R-37R | EBITDA = 12% revenue proxy
A25: C024 | B25: Reddi Services | C25: Danny Ray Gravatt | D25: (913) 731-0237 | E25: 49 | F25: 1154000 | G25: 9615000 | H25: HVAC + Plumbing | I25: Peoria | J25: AZ | K25: (602) 789-3910 | L25: danny@reddiservices.com | M25: 1. Not Contacted | N25: Unknown | O25: =IF(B25="","",IFERROR(LOOKUP(2,1/('Call Log'!$C$2:$C$5000=B25),'Call Log'!$B$2:$B$5000),"")) | P25: =IF(B25="","",COUNTIFS('Call Log'!$C$2:$C$5000,B25,'Call Log'!$A$2:$A$5000,">="&(TODAY()-WEEKDAY(TODAY(),2)+1))) -> 0 | Q25: =IF(B25="","",COUNTIF('Call Log'!$C$2:$C$5000,B25)) -> 0 | R25: =IF(B25="","",IFERROR(IF(MAXIFS('Call Log'!$A$2:$A$5000,'Call Log'!$C$2:$C$5000,B25)=0,"",MAXIFS('Call Log'!$A$2:$A$5000,'Call Log'!$C$2:$C$5000,B25)),"")) | Z25: roc-posting-list | AA25: Contact title 'Division Manager Plumbing, Excavation and Liquid Waste Hauling' - verify decision maker | ROC 202706 CR-37 | EBITDA = 12% revenue proxy
A26: C025 | B26: Temperature Control, Inc. A/C-Heating & Plumbing - Tucson, AZ | C26: Vance Macleod | D26: (520) 314-2110 | E26: 12 | F26: 1105000 | G26: 9212000 | H26: HVAC | I26: Tucson | J26: AZ | K26: (520) 775-3566 | M26: 1. Not Contacted | N26: Unknown | O26: =IF(B26="","",IFERROR(LOOKUP(2,1/('Call Log'!$C$2:$C$5000=B26),'Call Log'!$B$2:$B$5000),"")) | P26: =IF(B26="","",COUNTIFS('Call Log'!$C$2:$C$5000,B26,'Call Log'!$A$2:$A$5000,">="&(TODAY()-WEEKDAY(TODAY(),2)+1))) -> 0 | Q26: =IF(B26="","",COUNTIF('Call Log'!$C$2:$C$5000,B26)) -> 0 | R26: =IF(B26="","",IFERROR(IF(MAXIFS('Call Log'!$A$2:$A$5000,'Call Log'!$C$2:$C$5000,B26)=0,"",MAXIFS('Call Log'!$A$2:$A$5000,'Call Log'!$C$2:$C$5000,B26)),"")) | AA26: Owner found via Apollo | EBITDA = 12% revenue proxy
A27: C026 | B27: Temperature Control, Inc. A/C-Heating & Plumbing - Oro Valley, AZ | C27: Vance Macleod | D27: (520) 314-2110 | E27: 12 | F27: 1105000 | G27: 9212000 | H27: HVAC + Plumbing | I27: Tucson | J27: AZ | K27: (520) 201-5414 | M27: 1. Not Contacted | N27: Unknown | O27: =IF(B27="","",IFERROR(LOOKUP(2,1/('Call Log'!$C$2:$C$5000=B27),'Call Log'!$B$2:$B$5000),"")) | P27: =IF(B27="","",COUNTIFS('Call Log'!$C$2:$C$5000,B27,'Call Log'!$A$2:$A$5000,">="&(TODAY()-WEEKDAY(TODAY(),2)+1))) -> 0 | Q27: =IF(B27="","",COUNTIF('Call Log'!$C$2:$C$5000,B27)) -> 0 | R27: =IF(B27="","",IFERROR(IF(MAXIFS('Call Log'!$A$2:$A$5000,'Call Log'!$C$2:$C$5000,B27)=0,"",MAXIFS('Call Log'!$A$2:$A$5000,'Call Log'!$C$2:$C$5000,B27)),"")) | AA27: Owner found via Apollo | EBITDA = 12% revenue proxy
A28: C027 | B28: Anthony James Air Conditioning & Heating | C28: Anthony James Garcia | D28: (623) 670-1974 | E28: 1 | F28: 1101000 | G28: 9176000 | H28: HVAC | I28: Peoria | J28: AZ | K28: (623) 556-3852 | M28: 1. Not Contacted | N28: Unknown | O28: =IF(B28="","",IFERROR(LOOKUP(2,1/('Call Log'!$C$2:$C$5000=B28),'Call Log'!$B$2:$B$5000),"")) | P28: =IF(B28="","",COUNTIFS('Call Log'!$C$2:$C$5000,B28,'Call Log'!$A$2:$A$5000,">="&(TODAY()-WEEKDAY(TODAY(),2)+1))) -> 0 | Q28: =IF(B28="","",COUNTIF('Call Log'!$C$2:$C$5000,B28)) -> 0 | R28: =IF(B28="","",IFERROR(IF(MAXIFS('Call Log'!$A$2:$A$5000,'Call Log'!$C$2:$C$5000,B28)=0,"",MAXIFS('Call Log'!$A$2:$A$5000,'Call Log'!$C$2:$C$5000,B28)),"")) | Z28: roc-posting-list | AA28: Contact title 'Co Owner' - verify decision maker | ROC 240848 R-39 | EBITDA = 12% revenue proxy
A29: C028 | B29: DeGeorge Plumbing and HVAC | C29: Timothy L Chatburn | D29: +1 312-975-8109 | E29: 2 | F29: 1050000 | G29: 8753000 | H29: Plumbing | I29: Phoenix | J29: AZ | K29: (602) 830-3977 | M29: 1. Not Contacted | N29: Unknown | O29: =IF(B29="","",IFERROR(LOOKUP(2,1/('Call Log'!$C$2:$C$5000=B29),'Call Log'!$B$2:$B$5000),"")) | P29: =IF(B29="","",COUNTIFS('Call Log'!$C$2:$C$5000,B29,'Call Log'!$A$2:$A$5000,">="&(TODAY()-WEEKDAY(TODAY(),2)+1))) -> 0 | Q29: =IF(B29="","",COUNTIF('Call Log'!$C$2:$C$5000,B29)) -> 0 | R29: =IF(B29="","",IFERROR(IF(MAXIFS('Call Log'!$A$2:$A$5000,'Call Log'!$C$2:$C$5000,B29)=0,"",MAXIFS('Call Log'!$A$2:$A$5000,'Call Log'!$C$2:$C$5000,B29)),"")) | Z29: roc-posting-list | AA29: Cell pulled from Apollo contacts | ROC 342832 CR-77 | EBITDA = 12% revenue proxy
A30: C029 | B30: Hobaica Services | C30: Louis Gerard Hobaica | D30: (602) 721-1389 | E30: 32 | F30: 1032000 | G30: 8600000 | H30: HVAC | I30: Phoenix | J30: AZ | K30: (602) 675-8338 | L30: lhobaica@hobaica.com | M30: 1. Not Contacted | N30: Unknown | O30: =IF(B30="","",IFERROR(LOOKUP(2,1/('Call Log'!$C$2:$C$5000=B30),'Call Log'!$B$2:$B$5000),"")) | P30: =IF(B30="","",COUNTIFS('Call Log'!$C$2:$C$5000,B30,'Call Log'!$A$2:$A$5000,">="&(TODAY()-WEEKDAY(TODAY(),2)+1))) -> 0 | Q30: =IF(B30="","",COUNTIF('Call Log'!$C$2:$C$5000,B30)) -> 0 | R30: =IF(B30="","",IFERROR(IF(MAXIFS('Call Log'!$A$2:$A$5000,'Call Log'!$C$2:$C$5000,B30)=0,"",MAXIFS('Call Log'!$A$2:$A$5000,'Call Log'!$C$2:$C$5000,B30)),"")) | Z30: roc-posting-list | AA30: Co-owners: Brian Lee Sorensen | ROC 334988 CR-77 | EBITDA = 12% revenue proxy
A31: C030 | B31: Advantage Home Performance Inc. | C31: Michael William Uniacke | D31: (520) 717-2879 | E31: 4 | F31: 990000 | G31: 8254000 | H31: HVAC | I31: Prescott | J31: AZ | K31: (928) 445-3828 | M31: 1. Not Contacted | N31: Unknown | O31: =IF(B31="","",IFERROR(LOOKUP(2,1/('Call Log'!$C$2:$C$5000=B31),'Call Log'!$B$2:$B$5000),"")) | P31: =IF(B31="","",COUNTIFS('Call Log'!$C$2:$C$5000,B31,'Call Log'!$A$2:$A$5000,">="&(TODAY()-WEEKDAY(TODAY(),2)+1))) -> 0 | Q31: =IF(B31="","",COUNTIF('Call Log'!$C$2:$C$5000,B31)) -> 0 | R31: =IF(B31="","",IFERROR(IF(MAXIFS('Call Log'!$A$2:$A$5000,'Call Log'!$C$2:$C$5000,B31)=0,"",MAXIFS('Call Log'!$A$2:$A$5000,'Call Log'!$C$2:$C$5000,B31)),"")) | Z31: roc-posting-list | AA31: Other locations: Glendale | ROC 274862 R-39R | EBITDA = 12% revenue proxy
A32: C031 | B32: Semper Fi Heating and Cooling | C32: Jesse Keenan | D32: (504) 682-8800 | E32: 96 | F32: 972000 | G32: 8100000 | H32: HVAC | I32: Mesa | J32: AZ | K32: (480) 741-1440 | L32: jesse@semperfiheatingcooling.com | M32: 1. Not Contacted | N32: Unknown | O32: =IF(B32="","",IFERROR(LOOKUP(2,1/('Call Log'!$C$2:$C$5000=B32),'Call Log'!$B$2:$B$5000),"")) | P32: =IF(B32="","",COUNTIFS('Call Log'!$C$2:$C$5000,B32,'Call Log'!$A$2:$A$5000,">="&(TODAY()-WEEKDAY(TODAY(),2)+1))) -> 0 | Q32: =IF(B32="","",COUNTIF('Call Log'!$C$2:$C$5000,B32)) -> 0 | R32: =IF(B32="","",IFERROR(IF(MAXIFS('Call Log'!$A$2:$A$5000,'Call Log'!$C$2:$C$5000,B32)=0,"",MAXIFS('Call Log'!$A$2:$A$5000,'Call Log'!$C$2:$C$5000,B32)),"")) | Z32: roc-posting-list | AA32: Co-owners: Steve Best | Other locations: Peoria | ROC 309388 R-39R | EBITDA = 12% revenue proxy
A33: C032 | B33: Done Rite Services - HVAC, Plumbing, & Electrical | C33: Christopher Deraffele | D33: (480) 246-7298 | E33: 42 | F33: 852000 | G33: 7100000 | H33: HVAC | I33: Tucson | J33: AZ | K33: (520) 369-3966 | M33: 1. Not Contacted | N33: Unknown | O33: =IF(B33="","",IFERROR(LOOKUP(2,1/('Call Log'!$C$2:$C$5000=B33),'Call Log'!$B$2:$B$5000),"")) | P33: =IF(B33="","",COUNTIFS('Call Log'!$C$2:$C$5000,B33,'Call Log'!$A$2:$A$5000,">="&(TODAY()-WEEKDAY(TODAY(),2)+1))) -> 0 | Q33: =IF(B33="","",COUNTIF('Call Log'!$C$2:$C$5000,B33)) -> 0 | R33: =IF(B33="","",IFERROR(IF(MAXIFS('Call Log'!$A$2:$A$5000,'Call Log'!$C$2:$C$5000,B33)=0,"",MAXIFS('Call Log'!$A$2:$A$5000,'Call Log'!$C$2:$C$5000,B33)),"")) | AA33: Contact title 'Owner' - verify decision maker | Owner found via Apollo | EBITDA = 12% revenue proxy
A34: C033 | B34: Hansberger Refrigeration and Electric Company | C34: Mark Allen Hansberger | D34: (928) 783-1729 | E34: 10 | F34: 787000 | G34: 6561000 | H34: HVAC | I34: Yuma | J34: AZ | K34: (928) 783-3331 | L34: markh@hreaz.com | M34: 1. Not Contacted | N34: Unknown | O34: =IF(B34="","",IFERROR(LOOKUP(2,1/('Call Log'!$C$2:$C$5000=B34),'Call Log'!$B$2:$B$5000),"")) | P34: =IF(B34="","",COUNTIFS('Call Log'!$C$2:$C$5000,B34,'Call Log'!$A$2:$A$5000,">="&(TODAY()-WEEKDAY(TODAY(),2)+1))) -> 0 | Q34: =IF(B34="","",COUNTIF('Call Log'!$C$2:$C$5000,B34)) -> 0 | R34: =IF(B34="","",IFERROR(IF(MAXIFS('Call Log'!$A$2:$A$5000,'Call Log'!$C$2:$C$5000,B34)=0,"",MAXIFS('Call Log'!$A$2:$A$5000,'Call Log'!$C$2:$C$5000,B34)),"")) | Z34: roc-posting-list | AA34: ROC 161695 CR-39 | EBITDA = 12% revenue proxy
A35: C034 | B35: North Valley Mechanical HVAC & Plumbing | C35: Kirk Buscho | D35: (602) 448-5255 | E35: 15 | F35: 703000 | G35: 5860000 | H35: HVAC | I35: Phoenix | J35: AZ | K35: (602) 975-4247 | M35: 1. Not Contacted | N35: Unknown | O35: =IF(B35="","",IFERROR(LOOKUP(2,1/('Call Log'!$C$2:$C$5000=B35),'Call Log'!$B$2:$B$5000),"")) | P35: =IF(B35="","",COUNTIFS('Call Log'!$C$2:$C$5000,B35,'Call Log'!$A$2:$A$5000,">="&(TODAY()-WEEKDAY(TODAY(),2)+1))) -> 0 | Q35: =IF(B35="","",COUNTIF('Call Log'!$C$2:$C$5000,B35)) -> 0 | R35: =IF(B35="","",IFERROR(IF(MAXIFS('Call Log'!$A$2:$A$5000,'Call Log'!$C$2:$C$5000,B35)=0,"",MAXIFS('Call Log'!$A$2:$A$5000,'Call Log'!$C$2:$C$5000,B35)),"")) | Z35: roc-posting-list | AA35: ROC 281777 CR-79 | EBITDA = 12% revenue proxy
A36: C035 | B36: Lee's Air, Plumbing, & Heating | C36: Thomas Edward Howard | D36: (559) 259-1244 | E36: 98 | F36: 684000 | G36: 5700000 | H36: HVAC | I36: Peoria | J36: AZ | K36: (602) 649-2180 | L36: thoward@servicetitan.com | M36: 1. Not Contacted | N36: Unknown | O36: =IF(B36="","",IFERROR(LOOKUP(2,1/('Call Log'!$C$2:$C$5000=B36),'Call Log'!$B$2:$B$5000),"")) | P36: =IF(B36="","",COUNTIFS('Call Log'!$C$2:$C$5000,B36,'Call Log'!$A$2:$A$5000,">="&(TODAY()-WEEKDAY(TODAY(),2)+1))) -> 0 | Q36: =IF(B36="","",COUNTIF('Call Log'!$C$2:$C$5000,B36)) -> 0 | R36: =IF(B36="","",IFERROR(IF(MAXIFS('Call Log'!$A$2:$A$5000,'Call Log'!$C$2:$C$5000,B36)=0,"",MAXIFS('Call Log'!$A$2:$A$5000,'Call Log'!$C$2:$C$5000,B36)),"")) | Z36: roc-posting-list | AA36: Contact title 'VP Customer Experience' - verify decision maker | ROC 358197 CR-37 | EBITDA = 12% revenue proxy
A37: C036 | B37: Ambient Edge Heating, Air Conditioning & Refrigeration Inc. | C37: Steven Lewis | D37: (928) 279-1017 | E37: 30 | F37: 681000 | G37: 5676000 | H37: HVAC + Plumbing | I37: Kingman | J37: AZ | K37: (928) 615-8224 | L37: slewis@ambientedge.com | M37: 1. Not Contacted | N37: Unknown | O37: =IF(B37="","",IFERROR(LOOKUP(2,1/('Call Log'!$C$2:$C$5000=B37),'Call Log'!$B$2:$B$5000),"")) | P37: =IF(B37="","",COUNTIFS('Call Log'!$C$2:$C$5000,B37,'Call Log'!$A$2:$A$5000,">="&(TODAY()-WEEKDAY(TODAY(),2)+1))) -> 0 | Q37: =IF(B37="","",COUNTIF('Call Log'!$C$2:$C$5000,B37)) -> 0 | R37: =IF(B37="","",IFERROR(IF(MAXIFS('Call Log'!$A$2:$A$5000,'Call Log'!$C$2:$C$5000,B37)=0,"",MAXIFS('Call Log'!$A$2:$A$5000,'Call Log'!$C$2:$C$5000,B37)),"")) | AA37: Owner found via Apollo | EBITDA = 12% revenue proxy
A38: C037 | B38: Ambient Edge Cooling, Heating & Plumbing | C38: Steven Ray Lewis | D38: (928) 279-1017 | E38: 30 | F38: 681000 | G38: 5676000 | H38: HVAC | I38: Lake Havasu City | J38: AZ | K38: (928) 569-9545 | L38: slewis@ambientedge.com | M38: 1. Not Contacted | N38: Unknown | O38: =IF(B38="","",IFERROR(LOOKUP(2,1/('Call Log'!$C$2:$C$5000=B38),'Call Log'!$B$2:$B$5000),"")) | P38: =IF(B38="","",COUNTIFS('Call Log'!$C$2:$C$5000,B38,'Call Log'!$A$2:$A$5000,">="&(TODAY()-WEEKDAY(TODAY(),2)+1))) -> 0 | Q38: =IF(B38="","",COUNTIF('Call Log'!$C$2:$C$5000,B38)) -> 0 | R38: =IF(B38="","",IFERROR(IF(MAXIFS('Call Log'!$A$2:$A$5000,'Call Log'!$C$2:$C$5000,B38)=0,"",MAXIFS('Call Log'!$A$2:$A$5000,'Call Log'!$C$2:$C$5000,B38)),"")) | Z38: roc-posting-list | AA38: ROC 333029 CR-39 | EBITDA = 12% revenue proxy
A39: C038 | B39: Intelligent Design Air Conditioning, Plumbing, Solar, & Electric | C39: Andrew Dobbins | D39: (520) 780-7233 | E39: 16 | F39: 657000 | G39: 5476000 | H39: HVAC | I39: Tucson | J39: AZ | K39: (520) 333-2665 | L39: andrew@idesignac.com | M39: 1. Not Contacted | N39: Unknown | O39: =IF(B39="","",IFERROR(LOOKUP(2,1/('Call Log'!$C$2:$C$5000=B39),'Call Log'!$B$2:$B$5000),"")) | P39: =IF(B39="","",COUNTIFS('Call Log'!$C$2:$C$5000,B39,'Call Log'!$A$2:$A$5000,">="&(TODAY()-WEEKDAY(TODAY(),2)+1))) -> 0 | Q39: =IF(B39="","",COUNTIF('Call Log'!$C$2:$C$5000,B39)) -> 0 | R39: =IF(B39="","",IFERROR(IF(MAXIFS('Call Log'!$A$2:$A$5000,'Call Log'!$C$2:$C$5000,B39)=0,"",MAXIFS('Call Log'!$A$2:$A$5000,'Call Log'!$C$2:$C$5000,B39)),"")) | AA39: Owner found via Apollo | EBITDA = 12% revenue proxy
A40: C039 | B40: Collins Commercial Services | C40: Chad Christian Collins | D40: (480) 926-1975 | E40: 31 | F40: 615000 | G40: 5125000 | H40: Plumbing | I40: Scottsdale | J40: AZ | K40: (844) 493-2974 | L40: chad@collins-cs.com | M40: 1. Not Contacted | N40: Unknown | O40: =IF(B40="","",IFERROR(LOOKUP(2,1/('Call Log'!$C$2:$C$5000=B40),'Call Log'!$B$2:$B$5000),"")) | P40: =IF(B40="","",COUNTIFS('Call Log'!$C$2:$C$5000,B40,'Call Log'!$A$2:$A$5000,">="&(TODAY()-WEEKDAY(TODAY(),2)+1))) -> 0 | Q40: =IF(B40="","",COUNTIF('Call Log'!$C$2:$C$5000,B40)) -> 0 | R40: =IF(B40="","",IFERROR(IF(MAXIFS('Call Log'!$A$2:$A$5000,'Call Log'!$C$2:$C$5000,B40)=0,"",MAXIFS('Call Log'!$A$2:$A$5000,'Call Log'!$C$2:$C$5000,B40)),"")) | Z40: roc-posting-list | AA40: ROC 206292 CR-37 | EBITDA = 12% revenue proxy
A41: C040 | B41: Smith Plumbing, Heating and Cooling | C41: QP Exempt | D41: (434) 987-0184 | E41: 59 | F41: 606000 | G41: 5046000 | H41: Plumbing | I41: Mesa | J41: AZ | K41: (480) 827-9111 | M41: 1. Not Contacted | N41: Unknown | O41: =IF(B41="","",IFERROR(LOOKUP(2,1/('Call Log'!$C$2:$C$5000=B41),'Call Log'!$B$2:$B$5000),"")) | P41: =IF(B41="","",COUNTIFS('Call Log'!$C$2:$C$5000,B41,'Call Log'!$A$2:$A$5000,">="&(TODAY()-WEEKDAY(TODAY(),2)+1))) -> 0 | Q41: =IF(B41="","",COUNTIF('Call Log'!$C$2:$C$5000,B41)) -> 0 | R41: =IF(B41="","",IFERROR(IF(MAXIFS('Call Log'!$A$2:$A$5000,'Call Log'!$C$2:$C$5000,B41)=0,"",MAXIFS('Call Log'!$A$2:$A$5000,'Call Log'!$C$2:$C$5000,B41)),"")) | Z41: roc-apify | AA41: ROC 263352 | EBITDA = 12% revenue proxy
A42: C041 | B42: Cool Breeze Comfort Solutions | C42: Courtney Christine Allison | D42: (520) 907-1025 | E42: 30 | F42: 540000 | G42: 4504000 | H42: HVAC | I42: Tucson | J42: AZ | K42: (520) 495-2227 | L42: courtneya@coolbreezecs.com | M42: 1. Not Contacted | N42: Unknown | O42: =IF(B42="","",IFERROR(LOOKUP(2,1/('Call Log'!$C$2:$C$5000=B42),'Call Log'!$B$2:$B$5000),"")) | P42: =IF(B42="","",COUNTIFS('Call Log'!$C$2:$C$5000,B42,'Call Log'!$A$2:$A$5000,">="&(TODAY()-WEEKDAY(TODAY(),2)+1))) -> 0 | Q42: =IF(B42="","",COUNTIF('Call Log'!$C$2:$C$5000,B42)) -> 0 | R42: =IF(B42="","",IFERROR(IF(MAXIFS('Call Log'!$A$2:$A$5000,'Call Log'!$C$2:$C$5000,B42)=0,"",MAXIFS('Call Log'!$A$2:$A$5000,'Call Log'!$C$2:$C$5000,B42)),"")) | Z42: roc-posting-list | AA42: Other locations: Pinetop | ROC 289247 CR-39 | EBITDA = 12% revenue proxy | Size est. midpoint - ZoomInfo: 11-50 employees
A43: C042 | B43: Comfort Experts | C43: Joseph Matthew Gonzales | D43: +1 480-628-0965 | E43: 2 | F43: 535000 | G43: 4455000 | H43: HVAC | I43: Mesa | J43: AZ | K43: (480) 351-5672 | M43: 1. Not Contacted | N43: Unknown | O43: =IF(B43="","",IFERROR(LOOKUP(2,1/('Call Log'!$C$2:$C$5000=B43),'Call Log'!$B$2:$B$5000),"")) | P43: =IF(B43="","",COUNTIFS('Call Log'!$C$2:$C$5000,B43,'Call Log'!$A$2:$A$5000,">="&(TODAY()-WEEKDAY(TODAY(),2)+1))) -> 0 | Q43: =IF(B43="","",COUNTIF('Call Log'!$C$2:$C$5000,B43)) -> 0 | R43: =IF(B43="","",IFERROR(IF(MAXIFS('Call Log'!$A$2:$A$5000,'Call Log'!$C$2:$C$5000,B43)=0,"",MAXIFS('Call Log'!$A$2:$A$5000,'Call Log'!$C$2:$C$5000,B43)),"")) | Z43: roc-apify | AA43: Cell pulled from Apollo contacts | ROC 309536 | EBITDA = 12% revenue proxy
A44: C043 | B44: Brewer’s Air Conditioning & Heating | C44: Mark Ybarra | D44: (480) 201-6004 | E44: 5 | F44: 505000 | G44: 4208000 | H44: HVAC | I44: Tempe | J44: AZ | K44: (480) 725-5454 | L44: mybarra@brewersac.com | M44: 1. Not Contacted | N44: Unknown | O44: =IF(B44="","",IFERROR(LOOKUP(2,1/('Call Log'!$C$2:$C$5000=B44),'Call Log'!$B$2:$B$5000),"")) | P44: =IF(B44="","",COUNTIFS('Call Log'!$C$2:$C$5000,B44,'Call Log'!$A$2:$A$5000,">="&(TODAY()-WEEKDAY(TODAY(),2)+1))) -> 0 | Q44: =IF(B44="","",COUNTIF('Call Log'!$C$2:$C$5000,B44)) -> 0 | R44: =IF(B44="","",IFERROR(IF(MAXIFS('Call Log'!$A$2:$A$5000,'Call Log'!$C$2:$C$5000,B44)=0,"",MAXIFS('Call Log'!$A$2:$A$5000,'Call Log'!$C$2:$C$5000,B44)),"")) | Z44: roc-posting-list | AA44: Contact title 'Sales Consultant' - verify decision maker | ROC 312643 CR-39 | EBITDA = 12% revenue proxy
A45: C044 | B45: Deer Valley Plumbing & Air Conditioning - Phoenix | C45: Aubrey Dell | D45: (602) 570-5855 | E45: 22 | F45: 498000 | G45: 4152000 | H45: Plumbing | I45: Phoenix | J45: AZ | K45: (623) 343-3077 | L45: aubreyd@deervalleyplumbing.com | M45: 1. Not Contacted | N45: Unknown | O45: =IF(B45="","",IFERROR(LOOKUP(2,1/('Call Log'!$C$2:$C$5000=B45),'Call Log'!$B$2:$B$5000),"")) | P45: =IF(B45="","",COUNTIFS('Call Log'!$C$2:$C$5000,B45,'Call Log'!$A$2:$A$5000,">="&(TODAY()-WEEKDAY(TODAY(),2)+1))) -> 0 | Q45: =IF(B45="","",COUNTIF('Call Log'!$C$2:$C$5000,B45)) -> 0 | R45: =IF(B45="","",IFERROR(IF(MAXIFS('Call Log'!$A$2:$A$5000,'Call Log'!$C$2:$C$5000,B45)=0,"",MAXIFS('Call Log'!$A$2:$A$5000,'Call Log'!$C$2:$C$5000,B45)),"")) | AA45: Owner found via Apollo | EBITDA = 12% revenue proxy
A46: C045 | B46: City Wide Plumbing & Service Co. | C46: Larry Charles Quinn | D46: (704) 807-6522 | E46: 1 | F46: 466000 | G46: 3882000 | H46: Plumbing | I46: Tempe | J46: AZ | K46: (480) 966-8795 | M46: 1. Not Contacted | N46: Unknown | O46: =IF(B46="","",IFERROR(LOOKUP(2,1/('Call Log'!$C$2:$C$5000=B46),'Call Log'!$B$2:$B$5000),"")) | P46: =IF(B46="","",COUNTIFS('Call Log'!$C$2:$C$5000,B46,'Call Log'!$A$2:$A$5000,">="&(TODAY()-WEEKDAY(TODAY(),2)+1))) -> 0 | Q46: =IF(B46="","",COUNTIF('Call Log'!$C$2:$C$5000,B46)) -> 0 | R46: =IF(B46="","",IFERROR(IF(MAXIFS('Call Log'!$A$2:$A$5000,'Call Log'!$C$2:$C$5000,B46)=0,"",MAXIFS('Call Log'!$A$2:$A$5000,'Call Log'!$C$2:$C$5000,B46)),"")) | Z46: roc-posting-list | AA46: ROC 335199 CR-37 | EBITDA = 12% revenue proxy
A47: C046 | B47: Rooter Hero Plumbing & Air of Tempe | C47: Chris Coatsworth | D47: (818) 535-0768 | E47: 350 | F47: 446000 | G47: 3717000 | H47: Plumbing | I47: Tempe | J47: AZ | K47: (480) 646-3888 | L47: chris@aaaparadiseplumbing.com | M47: 1. Not Contacted | N47: Unknown | O47: =IF(B47="","",IFERROR(LOOKUP(2,1/('Call Log'!$C$2:$C$5000=B47),'Call Log'!$B$2:$B$5000),"")) | P47: =IF(B47="","",COUNTIFS('Call Log'!$C$2:$C$5000,B47,'Call Log'!$A$2:$A$5000,">="&(TODAY()-WEEKDAY(TODAY(),2)+1))) -> 0 | Q47: =IF(B47="","",COUNTIF('Call Log'!$C$2:$C$5000,B47)) -> 0 | R47: =IF(B47="","",IFERROR(IF(MAXIFS('Call Log'!$A$2:$A$5000,'Call Log'!$C$2:$C$5000,B47)=0,"",MAXIFS('Call Log'!$A$2:$A$5000,'Call Log'!$C$2:$C$5000,B47)),"")) | AA47: Owner found via Apollo | EBITDA = 12% revenue proxy
A48: C047 | B48: Before & After Plumbing and Drain, LLC | C48: Ryan Demilto | D48: (623) 203-3613 | E48: 1 | F48: 420000 | G48: 3502000 | H48: Plumbing | I48: Surprise | J48: AZ | K48: (623) 250-2584 | M48: 1. Not Contacted | N48: Unknown | O48: =IF(B48="","",IFERROR(LOOKUP(2,1/('Call Log'!$C$2:$C$5000=B48),'Call Log'!$B$2:$B$5000),"")) | P48: =IF(B48="","",COUNTIFS('Call Log'!$C$2:$C$5000,B48,'Call Log'!$A$2:$A$5000,">="&(TODAY()-WEEKDAY(TODAY(),2)+1))) -> 0 | Q48: =IF(B48="","",COUNTIF('Call Log'!$C$2:$C$5000,B48)) -> 0 | R48: =IF(B48="","",IFERROR(IF(MAXIFS('Call Log'!$A$2:$A$5000,'Call Log'!$C$2:$C$5000,B48)=0,"",MAXIFS('Call Log'!$A$2:$A$5000,'Call Log'!$C$2:$C$5000,B48)),"")) | Z48: roc-posting-list | AA48: ROC 271749 CR-37 | EBITDA = 12% revenue proxy
A49: C048 | B49: Four Seasons Home Services - Cave Creek, AZ | C49: Jessica Morriston | D49: (480) 980-2713 | E49: 2 | F49: 348000 | G49: 2896000 | H49: HVAC | I49: Cave Creek | J49: AZ | K49: (480) 489-3210 | L49: jessica@fourseasonshs.com | M49: 1. Not Contacted | N49: Unknown | O49: =IF(B49="","",IFERROR(LOOKUP(2,1/('Call Log'!$C$2:$C$5000=B49),'Call Log'!$B$2:$B$5000),"")) | P49: =IF(B49="","",COUNTIFS('Call Log'!$C$2:$C$5000,B49,'Call Log'!$A$2:$A$5000,">="&(TODAY()-WEEKDAY(TODAY(),2)+1))) -> 0 | Q49: =IF(B49="","",COUNTIF('Call Log'!$C$2:$C$5000,B49)) -> 0 | R49: =IF(B49="","",IFERROR(IF(MAXIFS('Call Log'!$A$2:$A$5000,'Call Log'!$C$2:$C$5000,B49)=0,"",MAXIFS('Call Log'!$A$2:$A$5000,'Call Log'!$C$2:$C$5000,B49)),"")) | AA49: Owner found via Apollo | EBITDA = 12% revenue proxy
A50: C049 | B50: Reeis Air Conditioning, Plumbing & Electrical | C50: David Robinson | D50: (480) 969-7504 | E50: 53 | F50: 329000 | G50: 2741000 | H50: HVAC | I50: Phoenix | J50: AZ | K50: (480) 581-5683 | L50: drobinson@reeis.com | M50: 1. Not Contacted | N50: Unknown | O50: =IF(B50="","",IFERROR(LOOKUP(2,1/('Call Log'!$C$2:$C$5000=B50),'Call Log'!$B$2:$B$5000),"")) | P50: =IF(B50="","",COUNTIFS('Call Log'!$C$2:$C$5000,B50,'Call Log'!$A$2:$A$5000,">="&(TODAY()-WEEKDAY(TODAY(),2)+1))) -> 0 | Q50: =IF(B50="","",COUNTIF('Call Log'!$C$2:$C$5000,B50)) -> 0 | R50: =IF(B50="","",IFERROR(IF(MAXIFS('Call Log'!$A$2:$A$5000,'Call Log'!$C$2:$C$5000,B50)=0,"",MAXIFS('Call Log'!$A$2:$A$5000,'Call Log'!$C$2:$C$5000,B50)),"")) | AA50: Contact title 'VP Outside Operations' - verify decision maker | Owner found via Apollo | EBITDA = 12% revenue proxy
A51: C050 | B51: Day & Night Air Conditioning, Heating, & Plumbing | C51: Steven Ray Lewis | D51: +1 602-739-1191 | E51: 50 | F51: 308000 | G51: 2567000 | H51: HVAC | I51: Phoenix | J51: AZ | K51: (602) 584-7758 | M51: 1. Not Contacted | N51: Unknown | O51: =IF(B51="","",IFERROR(LOOKUP(2,1/('Call Log'!$C$2:$C$5000=B51),'Call Log'!$B$2:$B$5000),"")) | P51: =IF(B51="","",COUNTIFS('Call Log'!$C$2:$C$5000,B51,'Call Log'!$A$2:$A$5000,">="&(TODAY()-WEEKDAY(TODAY(),2)+1))) -> 0 | Q51: =IF(B51="","",COUNTIF('Call Log'!$C$2:$C$5000,B51)) -> 0 | R51: =IF(B51="","",IFERROR(IF(MAXIFS('Call Log'!$A$2:$A$5000,'Call Log'!$C$2:$C$5000,B51)=0,"",MAXIFS('Call Log'!$A$2:$A$5000,'Call Log'!$C$2:$C$5000,B51)),"")) | Z51: roc-posting-list | AA51: Cell pulled from Apollo contacts | ROC 335883 CR-39 | EBITDA = 12% revenue proxy
A52: C051 | B52: Precision Air & Plumbing | C52: Erik Jason Bryan | D52: +1 480-522-8439 | E52: 40 | F52: 246000 | G52: 2048000 | H52: HVAC | I52: Chandler | J52: AZ | K52: (602) 490-8566 | M52: 1. Not Contacted | N52: Unknown | O52: =IF(B52="","",IFERROR(LOOKUP(2,1/('Call Log'!$C$2:$C$5000=B52),'Call Log'!$B$2:$B$5000),"")) | P52: =IF(B52="","",COUNTIFS('Call Log'!$C$2:$C$5000,B52,'Call Log'!$A$2:$A$5000,">="&(TODAY()-WEEKDAY(TODAY(),2)+1))) -> 0 | Q52: =IF(B52="","",COUNTIF('Call Log'!$C$2:$C$5000,B52)) -> 0 | R52: =IF(B52="","",IFERROR(IF(MAXIFS('Call Log'!$A$2:$A$5000,'Call Log'!$C$2:$C$5000,B52)=0,"",MAXIFS('Call Log'!$A$2:$A$5000,'Call Log'!$C$2:$C$5000,B52)),"")) | Z52: roc-posting-list | AA52: Cell pulled from Apollo contacts | ROC 126405 R-39R | EBITDA = 12% revenue proxy
A53: C052 | B53: McCall's Air Conditioning & Heating | C53: Alex McCall | D53: (480) 620-4003 | E53: 3 | F53: 129000 | G53: 1076000 | H53: HVAC | I53: Mesa | J53: AZ | K53: (480) 396-0041 | M53: 1. Not Contacted | N53: Unknown | O53: =IF(B53="","",IFERROR(LOOKUP(2,1/('Call Log'!$C$2:$C$5000=B53),'Call Log'!$B$2:$B$5000),"")) | P53: =IF(B53="","",COUNTIFS('Call Log'!$C$2:$C$5000,B53,'Call Log'!$A$2:$A$5000,">="&(TODAY()-WEEKDAY(TODAY(),2)+1))) -> 0 | Q53: =IF(B53="","",COUNTIF('Call Log'!$C$2:$C$5000,B53)) -> 0 | R53: =IF(B53="","",IFERROR(IF(MAXIFS('Call Log'!$A$2:$A$5000,'Call Log'!$C$2:$C$5000,B53)=0,"",MAXIFS('Call Log'!$A$2:$A$5000,'Call Log'!$C$2:$C$5000,B53)),"")) | Z53: site-scrape | AA53: Contact title 'Service Manager' - verify decision maker | EBITDA = 12% revenue proxy
A54: C053 | B54: Autumn Air Heating & Cooling | C54: Joshua David Nepa | D54: (623) 205-7308 | E54: 15 | F54: 128000 | G54: 1065000 | H54: HVAC | I54: Avondale | J54: AZ | K54: (602) 266-5247 | L54: joshua@callautumn.com | M54: 1. Not Contacted | N54: Unknown | O54: =IF(B54="","",IFERROR(LOOKUP(2,1/('Call Log'!$C$2:$C$5000=B54),'Call Log'!$B$2:$B$5000),"")) | P54: =IF(B54="","",COUNTIFS('Call Log'!$C$2:$C$5000,B54,'Call Log'!$A$2:$A$5000,">="&(TODAY()-WEEKDAY(TODAY(),2)+1))) -> 0 | Q54: =IF(B54="","",COUNTIF('Call Log'!$C$2:$C$5000,B54)) -> 0 | R54: =IF(B54="","",IFERROR(IF(MAXIFS('Call Log'!$A$2:$A$5000,'Call Log'!$C$2:$C$5000,B54)=0,"",MAXIFS('Call Log'!$A$2:$A$5000,'Call Log'!$C$2:$C$5000,B54)),"")) | Z54: roc-posting-list | AA54: ROC 187538 R-39R | EBITDA = 12% revenue proxy
A55: C054 | B55: Cure All Plumbing | C55: Jayson Harrison | D55: (480) 262-2994 | E55: 5 | F55: 74000 | G55: 617000 | H55: Plumbing | I55: Gilbert | J55: AZ | K55: (480) 895-5858 | L55: jayson@cureallplumbing.com | M55: 1. Not Contacted | N55: Unknown | O55: =IF(B55="","",IFERROR(LOOKUP(2,1/('Call Log'!$C$2:$C$5000=B55),'Call Log'!$B$2:$B$5000),"")) | P55: =IF(B55="","",COUNTIFS('Call Log'!$C$2:$C$5000,B55,'Call Log'!$A$2:$A$5000,">="&(TODAY()-WEEKDAY(TODAY(),2)+1))) -> 0 | Q55: =IF(B55="","",COUNTIF('Call Log'!$C$2:$C$5000,B55)) -> 0 | R55: =IF(B55="","",IFERROR(IF(MAXIFS('Call Log'!$A$2:$A$5000,'Call Log'!$C$2:$C$5000,B55)=0,"",MAXIFS('Call Log'!$A$2:$A$5000,'Call Log'!$C$2:$C$5000,B55)),"")) | Z55: roc-posting-list | AA55: ROC 204797 CR-37 | EBITDA = 12% revenue proxy
A56: C055 | B56: PlumbSmart Plumbing Heating and Air | C56: Wayne Decker | D56: (480) 326-1186 | E56: 28 | F56: 52000 | G56: 431000 | H56: Plumbing | I56: Mesa | J56: AZ | K56: (480) 654-8865 | M56: 1. Not Contacted | N56: Unknown | O56: =IF(B56="","",IFERROR(LOOKUP(2,1/('Call Log'!$C$2:$C$5000=B56),'Call Log'!$B$2:$B$5000),"")) | P56: =IF(B56="","",COUNTIFS('Call Log'!$C$2:$C$5000,B56,'Call Log'!$A$2:$A$5000,">="&(TODAY()-WEEKDAY(TODAY(),2)+1))) -> 0 | Q56: =IF(B56="","",COUNTIF('Call Log'!$C$2:$C$5000,B56)) -> 0 | R56: =IF(B56="","",IFERROR(IF(MAXIFS('Call Log'!$A$2:$A$5000,'Call Log'!$C$2:$C$5000,B56)=0,"",MAXIFS('Call Log'!$A$2:$A$5000,'Call Log'!$C$2:$C$5000,B56)),"")) | AA56: Owner found via Apollo | ROC 223709 CR-37 | EBITDA = 12% revenue proxy
A57: C056 | B57: Red Mountain Air Conditioning | C57: Terry Diedrick | D57: (602) 390-4877 | E57: 6 | F57: 48000 | G57: 397000 | H57: HVAC | I57: Mesa | J57: AZ | K57: (480) 878-7098 | M57: 1. Not Contacted | N57: Unknown | O57: =IF(B57="","",IFERROR(LOOKUP(2,1/('Call Log'!$C$2:$C$5000=B57),'Call Log'!$B$2:$B$5000),"")) | P57: =IF(B57="","",COUNTIFS('Call Log'!$C$2:$C$5000,B57,'Call Log'!$A$2:$A$5000,">="&(TODAY()-WEEKDAY(TODAY(),2)+1))) -> 0 | Q57: =IF(B57="","",COUNTIF('Call Log'!$C$2:$C$5000,B57)) -> 0 | R57: =IF(B57="","",IFERROR(IF(MAXIFS('Call Log'!$A$2:$A$5000,'Call Log'!$C$2:$C$5000,B57)=0,"",MAXIFS('Call Log'!$A$2:$A$5000,'Call Log'!$C$2:$C$5000,B57)),"")) | Z57: roc-apify | AA57: Contact title 'Owner/manager' - verify decision maker | ROC 281437 | EBITDA = 12% revenue proxy
A58: C057 | B58: Arizona's Dukes of Air & Plumbing | C58: Kevin Shay Styles | D58: (520) 238-1459 | E58: 30 | H58: HVAC | I58: Mesa | J58: AZ | K58: (480) 773-6565 | M58: 1. Not Contacted | N58: Unknown | O58: =IF(B58="","",IFERROR(LOOKUP(2,1/('Call Log'!$C$2:$C$5000=B58),'Call Log'!$B$2:$B$5000),"")) | P58: =IF(B58="","",COUNTIFS('Call Log'!$C$2:$C$5000,B58,'Call Log'!$A$2:$A$5000,">="&(TODAY()-WEEKDAY(TODAY(),2)+1))) -> 0 | Q58: =IF(B58="","",COUNTIF('Call Log'!$C$2:$C$5000,B58)) -> 0 | R58: =IF(B58="","",IFERROR(IF(MAXIFS('Call Log'!$A$2:$A$5000,'Call Log'!$C$2:$C$5000,B58)=0,"",MAXIFS('Call Log'!$A$2:$A$5000,'Call Log'!$C$2:$C$5000,B58)),"")) | Z58: roc-posting-list | AA58: VERIFY: Apollo matched a different/parent org | Co-owners: Michael D Read | Contact title 'Instructor' - verify decision maker | ROC 289250 CR-39 | Size est. midpoint - ZoomInfo: 11-50 employees (Service Experts-owned brand)
A59: C058 | B59: Cal's Plumbing Inc. | C59: Danny Smith | D59: (760) 634-2252 | E59: 6 | H59: Plumbing | I59: Tucson | J59: AZ | K59: (520) 729-2945 | L59: danny@calsplumbing.com | M59: 1. Not Contacted | N59: Unknown | O59: =IF(B59="","",IFERROR(LOOKUP(2,1/('Call Log'!$C$2:$C$5000=B59),'Call Log'!$B$2:$B$5000),"")) | P59: =IF(B59="","",COUNTIFS('Call Log'!$C$2:$C$5000,B59,'Call Log'!$A$2:$A$5000,">="&(TODAY()-WEEKDAY(TODAY(),2)+1))) -> 0 | Q59: =IF(B59="","",COUNTIF('Call Log'!$C$2:$C$5000,B59)) -> 0 | R59: =IF(B59="","",IFERROR(IF(MAXIFS('Call Log'!$A$2:$A$5000,'Call Log'!$C$2:$C$5000,B59)=0,"",MAXIFS('Call Log'!$A$2:$A$5000,'Call Log'!$C$2:$C$5000,B59)),"")) | AA59: Contact title 'Company Owner' - verify decision maker | Owner found via Apollo | ROC 146649 R-39R
A60: C059 | B60: APES HVAC & Plumbing | C60: Brian Garrison | D60: (480) 695-6690 | E60: 30 | H60: HVAC | I60: Phoenix | J60: AZ | K60: (623) 521-1172 | L60: brian@go4apes.com | M60: 1. Not Contacted | N60: Unknown | O60: =IF(B60="","",IFERROR(LOOKUP(2,1/('Call Log'!$C$2:$C$5000=B60),'Call Log'!$B$2:$B$5000),"")) | P60: =IF(B60="","",COUNTIFS('Call Log'!$C$2:$C$5000,B60,'Call Log'!$A$2:$A$5000,">="&(TODAY()-WEEKDAY(TODAY(),2)+1))) -> 0 | Q60: =IF(B60="","",COUNTIF('Call Log'!$C$2:$C$5000,B60)) -> 0 | R60: =IF(B60="","",IFERROR(IF(MAXIFS('Call Log'!$A$2:$A$5000,'Call Log'!$C$2:$C$5000,B60)=0,"",MAXIFS('Call Log'!$A$2:$A$5000,'Call Log'!$C$2:$C$5000,B60)),"")) | Z60: roc-posting-list | AA60: VERIFY: Apollo matched a different/parent org | ROC 305585 CR-37 | Size est. midpoint - ZoomInfo (Arizona Plumbing Expert Services): 11-50 employees
A61: C060 | B61: Canyon State Service Experts | C61: Larry Sather | D61: (604) 360-6567 | E61: 30 | H61: HVAC | I61: Surprise | J61: AZ | K61: (602) 844-4104 | M61: 1. Not Contacted | N61: Unknown | O61: =IF(B61="","",IFERROR(LOOKUP(2,1/('Call Log'!$C$2:$C$5000=B61),'Call Log'!$B$2:$B$5000),"")) | P61: =IF(B61="","",COUNTIFS('Call Log'!$C$2:$C$5000,B61,'Call Log'!$A$2:$A$5000,">="&(TODAY()-WEEKDAY(TODAY(),2)+1))) -> 0 | Q61: =IF(B61="","",COUNTIF('Call Log'!$C$2:$C$5000,B61)) -> 0 | R61: =IF(B61="","",IFERROR(IF(MAXIFS('Call Log'!$A$2:$A$5000,'Call Log'!$C$2:$C$5000,B61)=0,"",MAXIFS('Call Log'!$A$2:$A$5000,'Call Log'!$C$2:$C$5000,B61)),"")) | AA61: VERIFY: size data looks like parent/franchise org | Contact title 'Owner' - verify decision maker | Owner found via Apollo | Size est. midpoint - ZoomInfo (Canyon State AC, Heating & Plumbing): 11-50 employees
A62: C061 | B62: AC by J | C62: Bryce Allan Johnson | D62: (602) 292-0542 | E62: 34 | H62: HVAC | I62: Scottsdale | J62: AZ | K62: (602) 607-0943 | M62: 1. Not Contacted | N62: Unknown | O62: =IF(B62="","",IFERROR(LOOKUP(2,1/('Call Log'!$C$2:$C$5000=B62),'Call Log'!$B$2:$B$5000),"")) | P62: =IF(B62="","",COUNTIFS('Call Log'!$C$2:$C$5000,B62,'Call Log'!$A$2:$A$5000,">="&(TODAY()-WEEKDAY(TODAY(),2)+1))) -> 0 | Q62: =IF(B62="","",COUNTIF('Call Log'!$C$2:$C$5000,B62)) -> 0 | R62: =IF(B62="","",IFERROR(IF(MAXIFS('Call Log'!$A$2:$A$5000,'Call Log'!$C$2:$C$5000,B62)=0,"",MAXIFS('Call Log'!$A$2:$A$5000,'Call Log'!$C$2:$C$5000,B62)),"")) | Z62: roc-posting-list | AA62: Co-owners: David R Harvey; Jonathan Jack Harvey | ROC 77064 C-39
A63: C062 | B63: Gold Star Plumbing & Drain | C63: Michael Smith | D63: (480) 252-9020 | E63: 11 | H63: Plumbing | I63: Gilbert | J63: AZ | K63: (480) 405-0922 | L63: mike@goldstarhomeservicesaz.com | M63: 1. Not Contacted | N63: Unknown | O63: =IF(B63="","",IFERROR(LOOKUP(2,1/('Call Log'!$C$2:$C$5000=B63),'Call Log'!$B$2:$B$5000),"")) | P63: =IF(B63="","",COUNTIFS('Call Log'!$C$2:$C$5000,B63,'Call Log'!$A$2:$A$5000,">="&(TODAY()-WEEKDAY(TODAY(),2)+1))) -> 0 | Q63: =IF(B63="","",COUNTIF('Call Log'!$C$2:$C$5000,B63)) -> 0 | R63: =IF(B63="","",IFERROR(IF(MAXIFS('Call Log'!$A$2:$A$5000,'Call Log'!$C$2:$C$5000,B63)=0,"",MAXIFS('Call Log'!$A$2:$A$5000,'Call Log'!$C$2:$C$5000,B63)),"")) | AA63: Other locations: Flagstaff; Prescott Valley; Tempe | Owner found via Apollo | ROC 327327 CR-37
A64: C063 | B64: Pride Heating, Cooling, Plumbing and Electrical | C64: Benjamin Brian LaVergne | D64: (509) 860-1751 | E64: 30 | H64: HVAC + Plumbing | I64: Tucson | J64: AZ | K64: (520) 297-3520 | M64: 1. Not Contacted | N64: Unknown | O64: =IF(B64="","",IFERROR(LOOKUP(2,1/('Call Log'!$C$2:$C$5000=B64),'Call Log'!$B$2:$B$5000),"")) | P64: =IF(B64="","",COUNTIFS('Call Log'!$C$2:$C$5000,B64,'Call Log'!$A$2:$A$5000,">="&(TODAY()-WEEKDAY(TODAY(),2)+1))) -> 0 | Q64: =IF(B64="","",COUNTIF('Call Log'!$C$2:$C$5000,B64)) -> 0 | R64: =IF(B64="","",IFERROR(IF(MAXIFS('Call Log'!$A$2:$A$5000,'Call Log'!$C$2:$C$5000,B64)=0,"",MAXIFS('Call Log'!$A$2:$A$5000,'Call Log'!$C$2:$C$5000,B64)),"")) | Z64: roc-posting-list | AA64: Co-owners: Timothy Edward Cannon Jr | Other locations: Tucson | ROC 356279 CR-37 | Size est. midpoint - ZoomInfo (Pride Mechanical LLC): 11-50 employees
A65: C064 | B65: Larson Air Conditioning | C65: Jared Allan Larson | D65: +1 602-361-9093 | E65: 9 | H65: HVAC | I65: Scottsdale | J65: AZ | K65: (480) 470-1280 | L65: jlarson@larsonairaz.com | M65: 1. Not Contacted | N65: Unknown | O65: =IF(B65="","",IFERROR(LOOKUP(2,1/('Call Log'!$C$2:$C$5000=B65),'Call Log'!$B$2:$B$5000),"")) | P65: =IF(B65="","",COUNTIFS('Call Log'!$C$2:$C$5000,B65,'Call Log'!$A$2:$A$5000,">="&(TODAY()-WEEKDAY(TODAY(),2)+1))) -> 0 | Q65: =IF(B65="","",COUNTIF('Call Log'!$C$2:$C$5000,B65)) -> 0 | R65: =IF(B65="","",IFERROR(IF(MAXIFS('Call Log'!$A$2:$A$5000,'Call Log'!$C$2:$C$5000,B65)=0,"",MAXIFS('Call Log'!$A$2:$A$5000,'Call Log'!$C$2:$C$5000,B65)),"")) | Z65: roc-posting-list | AA65: Co-owners: Tyrone Rush Lindsay | Cell pulled from Apollo contacts | ROC 280247 CR-39
A66: C065 | B66: Same Day Air Repair | C66: Jonathan R Temper | D66: (480) 305-3302 | E66: 5 | H66: HVAC | I66: Phoenix | J66: AZ | K66: (602) 571-1728 | L66: jon@sdaraz.com | M66: 1. Not Contacted | N66: Unknown | O66: =IF(B66="","",IFERROR(LOOKUP(2,1/('Call Log'!$C$2:$C$5000=B66),'Call Log'!$B$2:$B$5000),"")) | P66: =IF(B66="","",COUNTIFS('Call Log'!$C$2:$C$5000,B66,'Call Log'!$A$2:$A$5000,">="&(TODAY()-WEEKDAY(TODAY(),2)+1))) -> 0 | Q66: =IF(B66="","",COUNTIF('Call Log'!$C$2:$C$5000,B66)) -> 0 | R66: =IF(B66="","",IFERROR(IF(MAXIFS('Call Log'!$A$2:$A$5000,'Call Log'!$C$2:$C$5000,B66)=0,"",MAXIFS('Call Log'!$A$2:$A$5000,'Call Log'!$C$2:$C$5000,B66)),"")) | Z66: roc-posting-list | AA66: ROC 276722 CR-39 | Size est. midpoint - ZoomInfo: 1-10 employees (Chandler AZ entity)
A67: C066 | B67: My Maricopa Plumber | C67: Toma Florenz Fitzgerald | D67: (480) 235-9073 | E67: 5 | H67: Plumbing | I67: Maricopa | J67: AZ | K67: (520) 509-7948 | M67: 1. Not Contacted | N67: Unknown | O67: =IF(B67="","",IFERROR(LOOKUP(2,1/('Call Log'!$C$2:$C$5000=B67),'Call Log'!$B$2:$B$5000),"")) | P67: =IF(B67="","",COUNTIFS('Call Log'!$C$2:$C$5000,B67,'Call Log'!$A$2:$A$5000,">="&(TODAY()-WEEKDAY(TODAY(),2)+1))) -> 0 | Q67: =IF(B67="","",COUNTIF('Call Log'!$C$2:$C$5000,B67)) -> 0 | R67: =IF(B67="","",IFERROR(IF(MAXIFS('Call Log'!$A$2:$A$5000,'Call Log'!$C$2:$C$5000,B67)=0,"",MAXIFS('Call Log'!$A$2:$A$5000,'Call Log'!$C$2:$C$5000,B67)),"")) | Z67: roc-posting-list | AA67: Contact title 'Management Team Member' - verify decision maker | ROC 259533 R-37R | Size est. midpoint - ZoomInfo: 1-10 employees
A68: C067 | B68: Lawson Family Plumbing Inc. | C68: Jason Matthew Pfeiffer | D68: (602) 339-8347 | E68: 17 | H68: Plumbing | I68: Gilbert | J68: AZ | K68: (602) 413-5790 | M68: 1. Not Contacted | N68: Unknown | O68: =IF(B68="","",IFERROR(LOOKUP(2,1/('Call Log'!$C$2:$C$5000=B68),'Call Log'!$B$2:$B$5000),"")) | P68: =IF(B68="","",COUNTIFS('Call Log'!$C$2:$C$5000,B68,'Call Log'!$A$2:$A$5000,">="&(TODAY()-WEEKDAY(TODAY(),2)+1))) -> 0 | Q68: =IF(B68="","",COUNTIF('Call Log'!$C$2:$C$5000,B68)) -> 0 | R68: =IF(B68="","",IFERROR(IF(MAXIFS('Call Log'!$A$2:$A$5000,'Call Log'!$C$2:$C$5000,B68)=0,"",MAXIFS('Call Log'!$A$2:$A$5000,'Call Log'!$C$2:$C$5000,B68)),"")) | Z68: roc-posting-list | AA68: Contact title 'Plumber' - verify decision maker | ROC 272014 R-37R
A69: C068 | B69: Trident Plumbing & Drain | C69: Jared Wayne Colegrove | D69: (623) 687-4772 | E69: 4 | H69: Plumbing | I69: Peoria | J69: AZ | K69: (623) 879-2020 | L69: jared@tridentplumbingllc.com | M69: 1. Not Contacted | N69: Unknown | O69: =IF(B69="","",IFERROR(LOOKUP(2,1/('Call Log'!$C$2:$C$5000=B69),'Call Log'!$B$2:$B$5000),"")) | P69: =IF(B69="","",COUNTIFS('Call Log'!$C$2:$C$5000,B69,'Call Log'!$A$2:$A$5000,">="&(TODAY()-WEEKDAY(TODAY(),2)+1))) -> 0 | Q69: =IF(B69="","",COUNTIF('Call Log'!$C$2:$C$5000,B69)) -> 0 | R69: =IF(B69="","",IFERROR(IF(MAXIFS('Call Log'!$A$2:$A$5000,'Call Log'!$C$2:$C$5000,B69)=0,"",MAXIFS('Call Log'!$A$2:$A$5000,'Call Log'!$C$2:$C$5000,B69)),"")) | Z69: roc-posting-list | AA69: Other locations: Phoenix | ROC 331536 CR-37
A70: C069 | B70: Ideal Air Conditioning and Insulation | C70: Alex M Williams | D70: (480) 284-9540 | E70: 10 | H70: HVAC | I70: Phoenix | J70: AZ | K70: (480) 573-7604 | L70: alex@idealairaz.com | M70: 1. Not Contacted | N70: Unknown | O70: =IF(B70="","",IFERROR(LOOKUP(2,1/('Call Log'!$C$2:$C$5000=B70),'Call Log'!$B$2:$B$5000),"")) | P70: =IF(B70="","",COUNTIFS('Call Log'!$C$2:$C$5000,B70,'Call Log'!$A$2:$A$5000,">="&(TODAY()-WEEKDAY(TODAY(),2)+1))) -> 0 | Q70: =IF(B70="","",COUNTIF('Call Log'!$C$2:$C$5000,B70)) -> 0 | R70: =IF(B70="","",IFERROR(IF(MAXIFS('Call Log'!$A$2:$A$5000,'Call Log'!$C$2:$C$5000,B70)=0,"",MAXIFS('Call Log'!$A$2:$A$5000,'Call Log'!$C$2:$C$5000,B70)),"")) | Z70: roc-apify | AA70: ROC 276318
A71: C070 | B71: Hansen Family Plumbing & Air | C71: Erik Richard Hansen | D71: (480) 636-9112 | E71: 10 | H71: HVAC + Plumbing | I71: Mesa | J71: AZ | K71: (602) 805-4836 | L71: erik@hansenfamilyplumbing.com | M71: 1. Not Contacted | N71: Unknown | O71: =IF(B71="","",IFERROR(LOOKUP(2,1/('Call Log'!$C$2:$C$5000=B71),'Call Log'!$B$2:$B$5000),"")) | P71: =IF(B71="","",COUNTIFS('Call Log'!$C$2:$C$5000,B71,'Call Log'!$A$2:$A$5000,">="&(TODAY()-WEEKDAY(TODAY(),2)+1))) -> 0 | Q71: =IF(B71="","",COUNTIF('Call Log'!$C$2:$C$5000,B71)) -> 0 | R71: =IF(B71="","",IFERROR(IF(MAXIFS('Call Log'!$A$2:$A$5000,'Call Log'!$C$2:$C$5000,B71)=0,"",MAXIFS('Call Log'!$A$2:$A$5000,'Call Log'!$C$2:$C$5000,B71)),"")) | Z71: roc-posting-list | AA71: ROC 287491 CR-37
A72: C071 | B72: Zest Plumbing & Drain | C72: Ronald A Degner | D72: (480) 522-8384 | E72: 1 | H72: Plumbing | I72: Scottsdale | J72: AZ | K72: (480) 718-7075 | M72: 1. Not Contacted | N72: Unknown | O72: =IF(B72="","",IFERROR(LOOKUP(2,1/('Call Log'!$C$2:$C$5000=B72),'Call Log'!$B$2:$B$5000),"")) | P72: =IF(B72="","",COUNTIFS('Call Log'!$C$2:$C$5000,B72,'Call Log'!$A$2:$A$5000,">="&(TODAY()-WEEKDAY(TODAY(),2)+1))) -> 0 | Q72: =IF(B72="","",COUNTIF('Call Log'!$C$2:$C$5000,B72)) -> 0 | R72: =IF(B72="","",IFERROR(IF(MAXIFS('Call Log'!$A$2:$A$5000,'Call Log'!$C$2:$C$5000,B72)=0,"",MAXIFS('Call Log'!$A$2:$A$5000,'Call Log'!$C$2:$C$5000,B72)),"")) | Z72: roc-posting-list | AA72: ROC 310821 CR-37
A73: C072 | B73: The Aussie Plumber | C73: James Lee Hill | D73: (516) 246-1647 | E73: 4 | H73: Plumbing | I73: Phoenix | J73: AZ | K73: (602) 820-5551 | L73: james@theaussieplumber.com | M73: 1. Not Contacted | N73: Unknown | O73: =IF(B73="","",IFERROR(LOOKUP(2,1/('Call Log'!$C$2:$C$5000=B73),'Call Log'!$B$2:$B$5000),"")) | P73: =IF(B73="","",COUNTIFS('Call Log'!$C$2:$C$5000,B73,'Call Log'!$A$2:$A$5000,">="&(TODAY()-WEEKDAY(TODAY(),2)+1))) -> 0 | Q73: =IF(B73="","",COUNTIF('Call Log'!$C$2:$C$5000,B73)) -> 0 | R73: =IF(B73="","",IFERROR(IF(MAXIFS('Call Log'!$A$2:$A$5000,'Call Log'!$C$2:$C$5000,B73)=0,"",MAXIFS('Call Log'!$A$2:$A$5000,'Call Log'!$C$2:$C$5000,B73)),"")) | Z73: roc-apify | AA73: ROC 335675
A74: C073 | B74: Angel Air Cooling & Heating, LLC | C74: Jacob Adam Angel | D74: (480) 282-0688 | E74: 5 | H74: HVAC | I74: Queen Creek | J74: AZ | K74: (480) 298-0353 | L74: jake@angelaircooling.com | M74: 1. Not Contacted | N74: Unknown | O74: =IF(B74="","",IFERROR(LOOKUP(2,1/('Call Log'!$C$2:$C$5000=B74),'Call Log'!$B$2:$B$5000),"")) | P74: =IF(B74="","",COUNTIFS('Call Log'!$C$2:$C$5000,B74,'Call Log'!$A$2:$A$5000,">="&(TODAY()-WEEKDAY(TODAY(),2)+1))) -> 0 | Q74: =IF(B74="","",COUNTIF('Call Log'!$C$2:$C$5000,B74)) -> 0 | R74: =IF(B74="","",IFERROR(IF(MAXIFS('Call Log'!$A$2:$A$5000,'Call Log'!$C$2:$C$5000,B74)=0,"",MAXIFS('Call Log'!$A$2:$A$5000,'Call Log'!$C$2:$C$5000,B74)),"")) | Z74: roc-posting-list | AA74: VERIFY: Apollo matched a different/parent org | ROC 227821 CR-39 | Size est. midpoint - ZoomInfo: 1-10 employees
A75: C074 | B75: Everest Air LLC | C75: Mark Robert Brimley | D75: (480) 688-9331 | H75: HVAC | I75: Mesa | J75: AZ | K75: (480) 828-2705 | L75: mark@everestairaz.com | M75: 1. Not Contacted | N75: Unknown | O75: =IF(B75="","",IFERROR(LOOKUP(2,1/('Call Log'!$C$2:$C$5000=B75),'Call Log'!$B$2:$B$5000),"")) | P75: =IF(B75="","",COUNTIFS('Call Log'!$C$2:$C$5000,B75,'Call Log'!$A$2:$A$5000,">="&(TODAY()-WEEKDAY(TODAY(),2)+1))) -> 0 | Q75: =IF(B75="","",COUNTIF('Call Log'!$C$2:$C$5000,B75)) -> 0 | R75: =IF(B75="","",IFERROR(IF(MAXIFS('Call Log'!$A$2:$A$5000,'Call Log'!$C$2:$C$5000,B75)=0,"",MAXIFS('Call Log'!$A$2:$A$5000,'Call Log'!$C$2:$C$5000,B75)),"")) | Z75: roc-apify | AA75: Contact title 'Owner/ Service Tech' - verify decision maker | ROC 332061
A76: C075 | B76: One Hour Heating & Air Conditioning® of Yuma | C76: ESTEBAN ESCOBAR | D76: +1 520-249-7437 | H76: HVAC | I76: Yuma | J76: AZ | K76: (928) 218-3797 | M76: 1. Not Contacted | N76: Unknown | O76: =IF(B76="","",IFERROR(LOOKUP(2,1/('Call Log'!$C$2:$C$5000=B76),'Call Log'!$B$2:$B$5000),"")) | P76: =IF(B76="","",COUNTIFS('Call Log'!$C$2:$C$5000,B76,'Call Log'!$A$2:$A$5000,">="&(TODAY()-WEEKDAY(TODAY(),2)+1))) -> 0 | Q76: =IF(B76="","",COUNTIF('Call Log'!$C$2:$C$5000,B76)) -> 0 | R76: =IF(B76="","",IFERROR(IF(MAXIFS('Call Log'!$A$2:$A$5000,'Call Log'!$C$2:$C$5000,B76)=0,"",MAXIFS('Call Log'!$A$2:$A$5000,'Call Log'!$C$2:$C$5000,B76)),"")) | Z76: roc-posting-list | AA76: VERIFY: size data looks like parent/franchise org | Co-owners: Matt Aycock | Cell pulled from Apollo contacts | ROC 277800 CR-39
A77: C076 | B77: Fusion Plumbing & Air | C77: sean Michael Stewart | D77: (520) 850-5445 | E77: 10 | H77: HVAC + Plumbing | I77: Tucson | J77: AZ | K77: (520) 328-8957 | L77: seanstewart@fusionplumbingaz.com | M77: 1. Not Contacted | N77: Unknown | O77: =IF(B77="","",IFERROR(LOOKUP(2,1/('Call Log'!$C$2:$C$5000=B77),'Call Log'!$B$2:$B$5000),"")) | P77: =IF(B77="","",COUNTIFS('Call Log'!$C$2:$C$5000,B77,'Call Log'!$A$2:$A$5000,">="&(TODAY()-WEEKDAY(TODAY(),2)+1))) -> 0 | Q77: =IF(B77="","",COUNTIF('Call Log'!$C$2:$C$5000,B77)) -> 0 | R77: =IF(B77="","",IFERROR(IF(MAXIFS('Call Log'!$A$2:$A$5000,'Call Log'!$C$2:$C$5000,B77)=0,"",MAXIFS('Call Log'!$A$2:$A$5000,'Call Log'!$C$2:$C$5000,B77)),"")) | Z77: roc-posting-list | AA77: ROC 331612 CR-39
A78: C077 | B78: Fast Layne Plumbing LLC | C78: David Scott Layne | D78: (760) 844-2417 | E78: 2 | H78: Plumbing | I78: San Tan Valley | J78: AZ | K78: (480) 576-6307 | M78: 1. Not Contacted | N78: Unknown | O78: =IF(B78="","",IFERROR(LOOKUP(2,1/('Call Log'!$C$2:$C$5000=B78),'Call Log'!$B$2:$B$5000),"")) | P78: =IF(B78="","",COUNTIFS('Call Log'!$C$2:$C$5000,B78,'Call Log'!$A$2:$A$5000,">="&(TODAY()-WEEKDAY(TODAY(),2)+1))) -> 0 | Q78: =IF(B78="","",COUNTIF('Call Log'!$C$2:$C$5000,B78)) -> 0 | R78: =IF(B78="","",IFERROR(IF(MAXIFS('Call Log'!$A$2:$A$5000,'Call Log'!$C$2:$C$5000,B78)=0,"",MAXIFS('Call Log'!$A$2:$A$5000,'Call Log'!$C$2:$C$5000,B78)),"")) | Z78: roc-posting-list | AA78: Co-owners: Alexander Gerard Fletcher | ROC 342362 R-37R
A79: C078 | B79: JMAC Heating & Cooling | C79: John Sidney McDowell | D79: (602) 315-5492 | E79: 4 | H79: HVAC | I79: Mesa | J79: AZ | K79: (602) 279-2665 | L79: john@crycool.com | M79: 1. Not Contacted | N79: Unknown | O79: =IF(B79="","",IFERROR(LOOKUP(2,1/('Call Log'!$C$2:$C$5000=B79),'Call Log'!$B$2:$B$5000),"")) | P79: =IF(B79="","",COUNTIFS('Call Log'!$C$2:$C$5000,B79,'Call Log'!$A$2:$A$5000,">="&(TODAY()-WEEKDAY(TODAY(),2)+1))) -> 0 | Q79: =IF(B79="","",COUNTIF('Call Log'!$C$2:$C$5000,B79)) -> 0 | R79: =IF(B79="","",IFERROR(IF(MAXIFS('Call Log'!$A$2:$A$5000,'Call Log'!$C$2:$C$5000,B79)=0,"",MAXIFS('Call Log'!$A$2:$A$5000,'Call Log'!$C$2:$C$5000,B79)),"")) | Z79: roc-posting-list | AA79: ROC 192343 CR-39
A80: C079 | B80: AZ Perfect Comfort Heating & Cooling | C80: Robin McCombs | D80: (623) 256-2131 | E80: 8 | H80: HVAC | I80: Phoenix | J80: AZ | K80: (602) 551-6223 | L80: robin@azperfectcomfort.com | M80: 1. Not Contacted | N80: Unknown | O80: =IF(B80="","",IFERROR(LOOKUP(2,1/('Call Log'!$C$2:$C$5000=B80),'Call Log'!$B$2:$B$5000),"")) | P80: =IF(B80="","",COUNTIFS('Call Log'!$C$2:$C$5000,B80,'Call Log'!$A$2:$A$5000,">="&(TODAY()-WEEKDAY(TODAY(),2)+1))) -> 0 | Q80: =IF(B80="","",COUNTIF('Call Log'!$C$2:$C$5000,B80)) -> 0 | R80: =IF(B80="","",IFERROR(IF(MAXIFS('Call Log'!$A$2:$A$5000,'Call Log'!$C$2:$C$5000,B80)=0,"",MAXIFS('Call Log'!$A$2:$A$5000,'Call Log'!$C$2:$C$5000,B80)),"")) | Z80: roc-posting-list | AA80: Contact title 'Managing Partner' - verify decision maker | ROC 300933 CR-39
A81: C080 | B81: Allied Electric, Heating & AC Repair | C81: Mario Traina | D81: (917) 374-3010 | E81: 12 | H81: HVAC | I81: Prescott | J81: AZ | K81: (928) 232-6477 | L81: mariotraina@callalliedelectric.com | M81: 1. Not Contacted | N81: Unknown | O81: =IF(B81="","",IFERROR(LOOKUP(2,1/('Call Log'!$C$2:$C$5000=B81),'Call Log'!$B$2:$B$5000),"")) | P81: =IF(B81="","",COUNTIFS('Call Log'!$C$2:$C$5000,B81,'Call Log'!$A$2:$A$5000,">="&(TODAY()-WEEKDAY(TODAY(),2)+1))) -> 0 | Q81: =IF(B81="","",COUNTIF('Call Log'!$C$2:$C$5000,B81)) -> 0 | R81: =IF(B81="","",IFERROR(IF(MAXIFS('Call Log'!$A$2:$A$5000,'Call Log'!$C$2:$C$5000,B81)=0,"",MAXIFS('Call Log'!$A$2:$A$5000,'Call Log'!$C$2:$C$5000,B81)),"")) | AA81: Other locations: Flagstaff; Prescott Valley | Owner found via Apollo
A82: C081 | B82: Phillips Heating & Cooling, Inc. | C82: Philip Charles Phillips | D82: (928) 366-6931 | E82: 14 | H82: HVAC | I82: Prescott | J82: AZ | K82: (928) 445-0282 | L82: philip@phillips-hvac.com | M82: 1. Not Contacted | N82: Unknown | O82: =IF(B82="","",IFERROR(LOOKUP(2,1/('Call Log'!$C$2:$C$5000=B82),'Call Log'!$B$2:$B$5000),"")) | P82: =IF(B82="","",COUNTIFS('Call Log'!$C$2:$C$5000,B82,'Call Log'!$A$2:$A$5000,">="&(TODAY()-WEEKDAY(TODAY(),2)+1))) -> 0 | Q82: =IF(B82="","",COUNTIF('Call Log'!$C$2:$C$5000,B82)) -> 0 | R82: =IF(B82="","",IFERROR(IF(MAXIFS('Call Log'!$A$2:$A$5000,'Call Log'!$C$2:$C$5000,B82)=0,"",MAXIFS('Call Log'!$A$2:$A$5000,'Call Log'!$C$2:$C$5000,B82)),"")) | Z82: roc-posting-list | AA82: Contact title 'President-CEO' - verify decision maker | ROC 273094 CR-39
A83: C082 | B83: Magic Touch Mechanical | C83: QP Exempt | D83: (480) 226-6400 | E83: 30 | H83: HVAC | I83: Mesa | J83: AZ | K83: (480) 855-8789 | M83: 1. Not Contacted | N83: Unknown | O83: =IF(B83="","",IFERROR(LOOKUP(2,1/('Call Log'!$C$2:$C$5000=B83),'Call Log'!$B$2:$B$5000),"")) | P83: =IF(B83="","",COUNTIFS('Call Log'!$C$2:$C$5000,B83,'Call Log'!$A$2:$A$5000,">="&(TODAY()-WEEKDAY(TODAY(),2)+1))) -> 0 | Q83: =IF(B83="","",COUNTIF('Call Log'!$C$2:$C$5000,B83)) -> 0 | R83: =IF(B83="","",IFERROR(IF(MAXIFS('Call Log'!$A$2:$A$5000,'Call Log'!$C$2:$C$5000,B83)=0,"",MAXIFS('Call Log'!$A$2:$A$5000,'Call Log'!$C$2:$C$5000,B83)),"")) | Z83: roc-apify | AA83: ROC 149818 | Size est. midpoint - ZoomInfo: 11-50 employees
A84: C083 | B84: Cave Creek Cooling Company | C84: Michael Leo DeGennaro | D84: (480) 440-6261 | E84: 5 | H84: HVAC | I84: Cave Creek | J84: AZ | K84: (480) 440-6261 | M84: 1. Not Contacted | N84: Unknown | O84: =IF(B84="","",IFERROR(LOOKUP(2,1/('Call Log'!$C$2:$C$5000=B84),'Call Log'!$B$2:$B$5000),"")) | P84: =IF(B84="","",COUNTIFS('Call Log'!$C$2:$C$5000,B84,'Call Log'!$A$2:$A$5000,">="&(TODAY()-WEEKDAY(TODAY(),2)+1))) -> 0 | Q84: =IF(B84="","",COUNTIF('Call Log'!$C$2:$C$5000,B84)) -> 0 | R84: =IF(B84="","",IFERROR(IF(MAXIFS('Call Log'!$A$2:$A$5000,'Call Log'!$C$2:$C$5000,B84)=0,"",MAXIFS('Call Log'!$A$2:$A$5000,'Call Log'!$C$2:$C$5000,B84)),"")) | Z84: roc-posting-list | AA84: Contact title 'Heating, Ventilation, and Air Conditioning Business Owner' - verify decision maker | ROC 319035 CR-39 | Size est. midpoint - ZoomInfo: 1-10 employees
A85: C084 | B85: MechaniCool | C85: Robert W Geng | D85: (602) 367-6378 | E85: 6 | H85: HVAC | I85: Apache Junction | J85: AZ | K85: (480) 248-7897 | L85: robert@mechanicoolaz.com | M85: 1. Not Contacted | N85: Unknown | O85: =IF(B85="","",IFERROR(LOOKUP(2,1/('Call Log'!$C$2:$C$5000=B85),'Call Log'!$B$2:$B$5000),"")) | P85: =IF(B85="","",COUNTIFS('Call Log'!$C$2:$C$5000,B85,'Call Log'!$A$2:$A$5000,">="&(TODAY()-WEEKDAY(TODAY(),2)+1))) -> 0 | Q85: =IF(B85="","",COUNTIF('Call Log'!$C$2:$C$5000,B85)) -> 0 | R85: =IF(B85="","",IFERROR(IF(MAXIFS('Call Log'!$A$2:$A$5000,'Call Log'!$C$2:$C$5000,B85)=0,"",MAXIFS('Call Log'!$A$2:$A$5000,'Call Log'!$C$2:$C$5000,B85)),"")) | Z85: roc-posting-list | AA85: Contact title 'Office Manager' - verify decision maker | ROC 294740 CR-39
A86: C085 | B86: Diamondback Plumbing | C86: Steve Martin Herzog | D86: (602) 721-8062 | E86: 12 | H86: Plumbing | I86: Phoenix | J86: AZ | K86: (602) 428-0910 | L86: steve@hqplumbingandair.com | M86: 1. Not Contacted | N86: Unknown | O86: =IF(B86="","",IFERROR(LOOKUP(2,1/('Call Log'!$C$2:$C$5000=B86),'Call Log'!$B$2:$B$5000),"")) | P86: =IF(B86="","",COUNTIFS('Call Log'!$C$2:$C$5000,B86,'Call Log'!$A$2:$A$5000,">="&(TODAY()-WEEKDAY(TODAY(),2)+1))) -> 0 | Q86: =IF(B86="","",COUNTIF('Call Log'!$C$2:$C$5000,B86)) -> 0 | R86: =IF(B86="","",IFERROR(IF(MAXIFS('Call Log'!$A$2:$A$5000,'Call Log'!$C$2:$C$5000,B86)=0,"",MAXIFS('Call Log'!$A$2:$A$5000,'Call Log'!$C$2:$C$5000,B86)),"")) | Z86: roc-apify | AA86: Contact title 'Chief CEO' - verify decision maker | ROC 140167
A87: C086 | B87: Mission Heating & Cooling, LLC | C87: Chandler Donald Macomber | D87: (520) 849-4297 | E87: 5 | H87: HVAC | I87: Tucson | J87: AZ | K87: (520) 675-4270 | M87: 1. Not Contacted | N87: Unknown | O87: =IF(B87="","",IFERROR(LOOKUP(2,1/('Call Log'!$C$2:$C$5000=B87),'Call Log'!$B$2:$B$5000),"")) | P87: =IF(B87="","",COUNTIFS('Call Log'!$C$2:$C$5000,B87,'Call Log'!$A$2:$A$5000,">="&(TODAY()-WEEKDAY(TODAY(),2)+1))) -> 0 | Q87: =IF(B87="","",COUNTIF('Call Log'!$C$2:$C$5000,B87)) -> 0 | R87: =IF(B87="","",IFERROR(IF(MAXIFS('Call Log'!$A$2:$A$5000,'Call Log'!$C$2:$C$5000,B87)=0,"",MAXIFS('Call Log'!$A$2:$A$5000,'Call Log'!$C$2:$C$5000,B87)),"")) | Z87: roc-posting-list | AA87: ROC 278080 CR-39 | Size est. midpoint - ZoomInfo: 1-10 employees
A88: C087 | B88: Island Breeze Air Conditioning & Heating LLC | C88: Darrel Simeon Deokielal | D88: (602) 616-8442 | E88: 30 | H88: HVAC | I88: Phoenix | J88: AZ | K88: (623) 692-6013 | L88: darrel@islandbreeze-ac.com | M88: 1. Not Contacted | N88: Unknown | O88: =IF(B88="","",IFERROR(LOOKUP(2,1/('Call Log'!$C$2:$C$5000=B88),'Call Log'!$B$2:$B$5000),"")) | P88: =IF(B88="","",COUNTIFS('Call Log'!$C$2:$C$5000,B88,'Call Log'!$A$2:$A$5000,">="&(TODAY()-WEEKDAY(TODAY(),2)+1))) -> 0 | Q88: =IF(B88="","",COUNTIF('Call Log'!$C$2:$C$5000,B88)) -> 0 | R88: =IF(B88="","",IFERROR(IF(MAXIFS('Call Log'!$A$2:$A$5000,'Call Log'!$C$2:$C$5000,B88)=0,"",MAXIFS('Call Log'!$A$2:$A$5000,'Call Log'!$C$2:$C$5000,B88)),"")) | Z88: roc-apify | AA88: ROC 327760 | Size est. midpoint - ZoomInfo: 11-50 employees
A89: C088 | B89: Cool Zone Air Conditioning & Heating | C89: David Joseph Flemm | D89: (623) 693-3483 | E89: 2 | H89: HVAC | I89: Phoenix | J89: AZ | K89: (623) 250-0012 | L89: dflemm@coolzoneair.com | M89: 1. Not Contacted | N89: Unknown | O89: =IF(B89="","",IFERROR(LOOKUP(2,1/('Call Log'!$C$2:$C$5000=B89),'Call Log'!$B$2:$B$5000),"")) | P89: =IF(B89="","",COUNTIFS('Call Log'!$C$2:$C$5000,B89,'Call Log'!$A$2:$A$5000,">="&(TODAY()-WEEKDAY(TODAY(),2)+1))) -> 0 | Q89: =IF(B89="","",COUNTIF('Call Log'!$C$2:$C$5000,B89)) -> 0 | R89: =IF(B89="","",IFERROR(IF(MAXIFS('Call Log'!$A$2:$A$5000,'Call Log'!$C$2:$C$5000,B89)=0,"",MAXIFS('Call Log'!$A$2:$A$5000,'Call Log'!$C$2:$C$5000,B89)),"")) | Z89: roc-posting-list | AA89: ROC 224753 CR-39
A90: C089 | B90: All Out Cooling & Heating | C90: George A Blitch | D90: (480) 298-4919 | E90: 3 | H90: HVAC | I90: Chandler | J90: AZ | K90: (480) 578-1370 | M90: 1. Not Contacted | N90: Unknown | O90: =IF(B90="","",IFERROR(LOOKUP(2,1/('Call Log'!$C$2:$C$5000=B90),'Call Log'!$B$2:$B$5000),"")) | P90: =IF(B90="","",COUNTIFS('Call Log'!$C$2:$C$5000,B90,'Call Log'!$A$2:$A$5000,">="&(TODAY()-WEEKDAY(TODAY(),2)+1))) -> 0 | Q90: =IF(B90="","",COUNTIF('Call Log'!$C$2:$C$5000,B90)) -> 0 | R90: =IF(B90="","",IFERROR(IF(MAXIFS('Call Log'!$A$2:$A$5000,'Call Log'!$C$2:$C$5000,B90)=0,"",MAXIFS('Call Log'!$A$2:$A$5000,'Call Log'!$C$2:$C$5000,B90)),"")) | Z90: roc-posting-list | AA90: Contact title 'Owner & CEO' - verify decision maker | ROC 302365 CR-39
A91: C090 | B91: Hoffman Heating & Cooling LLC | C91: Gary Hoffman | D91: (610) 816-1513 | E91: 1 | H91: HVAC | I91: Coolidge | J91: AZ | K91: (520) 233-7982 | M91: 1. Not Contacted | N91: Unknown | O91: =IF(B91="","",IFERROR(LOOKUP(2,1/('Call Log'!$C$2:$C$5000=B91),'Call Log'!$B$2:$B$5000),"")) | P91: =IF(B91="","",COUNTIFS('Call Log'!$C$2:$C$5000,B91,'Call Log'!$A$2:$A$5000,">="&(TODAY()-WEEKDAY(TODAY(),2)+1))) -> 0 | Q91: =IF(B91="","",COUNTIF('Call Log'!$C$2:$C$5000,B91)) -> 0 | R91: =IF(B91="","",IFERROR(IF(MAXIFS('Call Log'!$A$2:$A$5000,'Call Log'!$C$2:$C$5000,B91)=0,"",MAXIFS('Call Log'!$A$2:$A$5000,'Call Log'!$C$2:$C$5000,B91)),"")) | Z91: roc-posting-list | AA91: ROC 196966 R-39R
A92: C091 | B92: Phend Plumbing & Rooter LLC | C92: Peter Matthew Phend | D92: (480) 612-1074 | E92: 4 | H92: Plumbing | I92: Gilbert | J92: AZ | K92: (480) 388-6093 | M92: 1. Not Contacted | N92: Unknown | O92: =IF(B92="","",IFERROR(LOOKUP(2,1/('Call Log'!$C$2:$C$5000=B92),'Call Log'!$B$2:$B$5000),"")) | P92: =IF(B92="","",COUNTIFS('Call Log'!$C$2:$C$5000,B92,'Call Log'!$A$2:$A$5000,">="&(TODAY()-WEEKDAY(TODAY(),2)+1))) -> 0 | Q92: =IF(B92="","",COUNTIF('Call Log'!$C$2:$C$5000,B92)) -> 0 | R92: =IF(B92="","",IFERROR(IF(MAXIFS('Call Log'!$A$2:$A$5000,'Call Log'!$C$2:$C$5000,B92)=0,"",MAXIFS('Call Log'!$A$2:$A$5000,'Call Log'!$C$2:$C$5000,B92)),"")) | Z92: roc-apify | AA92: ROC 288046
A93: C092 | B93: Sky Blue Heating & Cooling | C93: Eagle Numkena | D93: (928) 892-9920 | E93: 6 | H93: HVAC | I93: Lakeside | J93: AZ | K93: (928) 205-1509 | L93: eagle@skybluehvac.com | M93: 1. Not Contacted | N93: Unknown | O93: =IF(B93="","",IFERROR(LOOKUP(2,1/('Call Log'!$C$2:$C$5000=B93),'Call Log'!$B$2:$B$5000),"")) | P93: =IF(B93="","",COUNTIFS('Call Log'!$C$2:$C$5000,B93,'Call Log'!$A$2:$A$5000,">="&(TODAY()-WEEKDAY(TODAY(),2)+1))) -> 0 | Q93: =IF(B93="","",COUNTIF('Call Log'!$C$2:$C$5000,B93)) -> 0 | R93: =IF(B93="","",IFERROR(IF(MAXIFS('Call Log'!$A$2:$A$5000,'Call Log'!$C$2:$C$5000,B93)=0,"",MAXIFS('Call Log'!$A$2:$A$5000,'Call Log'!$C$2:$C$5000,B93)),"")) | AA93: Owner found via Apollo
A94: C093 | B94: Team AIR-Zona HVAC Air Conditioning & Heating | C94: dustin star mitchell | D94: (480) 529-3775 | E94: 3 | H94: HVAC | I94: Queen Creek | J94: AZ | K94: (480) 887-4623 | L94: dustin@teamairzona.com | M94: 1. Not Contacted | N94: Unknown | O94: =IF(B94="","",IFERROR(LOOKUP(2,1/('Call Log'!$C$2:$C$5000=B94),'Call Log'!$B$2:$B$5000),"")) | P94: =IF(B94="","",COUNTIFS('Call Log'!$C$2:$C$5000,B94,'Call Log'!$A$2:$A$5000,">="&(TODAY()-WEEKDAY(TODAY(),2)+1))) -> 0 | Q94: =IF(B94="","",COUNTIF('Call Log'!$C$2:$C$5000,B94)) -> 0 | R94: =IF(B94="","",IFERROR(IF(MAXIFS('Call Log'!$A$2:$A$5000,'Call Log'!$C$2:$C$5000,B94)=0,"",MAXIFS('Call Log'!$A$2:$A$5000,'Call Log'!$C$2:$C$5000,B94)),"")) | Z94: roc-posting-list | AA94: ROC 310743 CR-39
A95: C094 | B95: Code Blue Plumbing | C95: John G Gruber | D95: (908) 296-6025 | E95: 7 | H95: Plumbing | I95: Tucson | J95: AZ | K95: (520) 297-9949 | L95: john@codeblueaz.com | M95: 1. Not Contacted | N95: Unknown | O95: =IF(B95="","",IFERROR(LOOKUP(2,1/('Call Log'!$C$2:$C$5000=B95),'Call Log'!$B$2:$B$5000),"")) | P95: =IF(B95="","",COUNTIFS('Call Log'!$C$2:$C$5000,B95,'Call Log'!$A$2:$A$5000,">="&(TODAY()-WEEKDAY(TODAY(),2)+1))) -> 0 | Q95: =IF(B95="","",COUNTIF('Call Log'!$C$2:$C$5000,B95)) -> 0 | R95: =IF(B95="","",IFERROR(IF(MAXIFS('Call Log'!$A$2:$A$5000,'Call Log'!$C$2:$C$5000,B95)=0,"",MAXIFS('Call Log'!$A$2:$A$5000,'Call Log'!$C$2:$C$5000,B95)),"")) | Z95: roc-posting-list | AA95: ROC 319497 CR-37
A96: C095 | B96: Talbot Plumbing Services LLC | C96: Trever Jay Talbot | D96: (480) 665-0170 | E96: 2 | H96: Plumbing | I96: Queen Creek | J96: AZ | K96: (480) 241-5375 | M96: 1. Not Contacted | N96: Unknown | O96: =IF(B96="","",IFERROR(LOOKUP(2,1/('Call Log'!$C$2:$C$5000=B96),'Call Log'!$B$2:$B$5000),"")) | P96: =IF(B96="","",COUNTIFS('Call Log'!$C$2:$C$5000,B96,'Call Log'!$A$2:$A$5000,">="&(TODAY()-WEEKDAY(TODAY(),2)+1))) -> 0 | Q96: =IF(B96="","",COUNTIF('Call Log'!$C$2:$C$5000,B96)) -> 0 | R96: =IF(B96="","",IFERROR(IF(MAXIFS('Call Log'!$A$2:$A$5000,'Call Log'!$C$2:$C$5000,B96)=0,"",MAXIFS('Call Log'!$A$2:$A$5000,'Call Log'!$C$2:$C$5000,B96)),"")) | Z96: roc-posting-list | AA96: ROC 323870 CR-37
A97: C096 | B97: Savage Air Conditioning | C97: David Lee Savage | D97: (602) 999-7683 | E97: 6 | H97: HVAC | I97: Tempe | J97: AZ | K97: (480) 916-4313 | L97: dsavage@savageac.com | M97: 1. Not Contacted | N97: Unknown | O97: =IF(B97="","",IFERROR(LOOKUP(2,1/('Call Log'!$C$2:$C$5000=B97),'Call Log'!$B$2:$B$5000),"")) | P97: =IF(B97="","",COUNTIFS('Call Log'!$C$2:$C$5000,B97,'Call Log'!$A$2:$A$5000,">="&(TODAY()-WEEKDAY(TODAY(),2)+1))) -> 0 | Q97: =IF(B97="","",COUNTIF('Call Log'!$C$2:$C$5000,B97)) -> 0 | R97: =IF(B97="","",IFERROR(IF(MAXIFS('Call Log'!$A$2:$A$5000,'Call Log'!$C$2:$C$5000,B97)=0,"",MAXIFS('Call Log'!$A$2:$A$5000,'Call Log'!$C$2:$C$5000,B97)),"")) | Z97: roc-posting-list | AA97: ROC 228019 R-39R
A98: C097 | B98: Miracle Man Plumbing Inc. | C98: Joseph Harold Diemert | D98: (928) 642-2949 | E98: 4 | H98: Plumbing | I98: Prescott Valley | J98: AZ | K98: (928) 288-0355 | M98: 1. Not Contacted | N98: Unknown | O98: =IF(B98="","",IFERROR(LOOKUP(2,1/('Call Log'!$C$2:$C$5000=B98),'Call Log'!$B$2:$B$5000),"")) | P98: =IF(B98="","",COUNTIFS('Call Log'!$C$2:$C$5000,B98,'Call Log'!$A$2:$A$5000,">="&(TODAY()-WEEKDAY(TODAY(),2)+1))) -> 0 | Q98: =IF(B98="","",COUNTIF('Call Log'!$C$2:$C$5000,B98)) -> 0 | R98: =IF(B98="","",IFERROR(IF(MAXIFS('Call Log'!$A$2:$A$5000,'Call Log'!$C$2:$C$5000,B98)=0,"",MAXIFS('Call Log'!$A$2:$A$5000,'Call Log'!$C$2:$C$5000,B98)),"")) | Z98: roc-posting-list | AA98: Contact title 'Plumbing contractor' - verify decision maker | Other locations: Prescott | ROC 206195 R-37R
A99: C098 | B99: Clark Heating and Cooling | C99: David Byron Clark | D99: (608) 436-7327 | E99: 5 | H99: HVAC | I99: Peoria | J99: AZ | K99: (602) 793-2477 | L99: davidclark@clarkheatandcool.com | M99: 1. Not Contacted | N99: Unknown | O99: =IF(B99="","",IFERROR(LOOKUP(2,1/('Call Log'!$C$2:$C$5000=B99),'Call Log'!$B$2:$B$5000),"")) | P99: =IF(B99="","",COUNTIFS('Call Log'!$C$2:$C$5000,B99,'Call Log'!$A$2:$A$5000,">="&(TODAY()-WEEKDAY(TODAY(),2)+1))) -> 0 | Q99: =IF(B99="","",COUNTIF('Call Log'!$C$2:$C$5000,B99)) -> 0 | R99: =IF(B99="","",IFERROR(IF(MAXIFS('Call Log'!$A$2:$A$5000,'Call Log'!$C$2:$C$5000,B99)=0,"",MAXIFS('Call Log'!$A$2:$A$5000,'Call Log'!$C$2:$C$5000,B99)),"")) | Z99: roc-posting-list | AA99: ROC 272689 C-39
A100: C099 | B100: Samson and Sons | C100: Mark Gooding | D100: (520) 437-3817 | E100: 1 | H100: HVAC | I100: Tucson | J100: AZ | K100: (520) 437-3014 | L100: mark@samsonandsonshvac.com | M100: 1. Not Contacted | N100: Unknown | O100: =IF(B100="","",IFERROR(LOOKUP(2,1/('Call Log'!$C$2:$C$5000=B100),'Call Log'!$B$2:$B$5000),"")) | P100: =IF(B100="","",COUNTIFS('Call Log'!$C$2:$C$5000,B100,'Call Log'!$A$2:$A$5000,">="&(TODAY()-WEEKDAY(TODAY(),2)+1))) -> 0 | Q100: =IF(B100="","",COUNTIF('Call Log'!$C$2:$C$5000,B100)) -> 0 | R100: =IF(B100="","",IFERROR(IF(MAXIFS('Call Log'!$A$2:$A$5000,'Call Log'!$C$2:$C$5000,B100)=0,"",MAXIFS('Call Log'!$A$2:$A$5000,'Call Log'!$C$2:$C$5000,B100)),"")) | Z100: roc-posting-list | AA100: ROC 299173 CR-39
...

Sheet Call Log
A1: Date | B1: Caller | C1: Company Name | D1: Reached | E1: Outcome | F1: Interest After Call | G1: Mins | H1: Call Summary | I1: Next Step | J1: Follow-Up Date

Sheet SMS Nurture
A1: Company (pick from list) | B1: Owner | C1: Owner Cell | D1: Date Added | E1: Said No To | F1: Last Text Sent | G1: Next Text Due | H1: Status | I1: Notes | K1: MONTHLY TEXT SCRIPTS - rotate so it never reads copy-paste. Send MANUALLY, one at a time, from your own phone.
B2: {=IF($A2="","",IFERROR(INDEX(Companies!$C$2:$C$1000,MATCH($A2,Companies!$B$2:$B$1000,0)),""))} | C2: {=IF($A2="","",IFERROR(INDEX(Companies!$D$2:$D$1000,MATCH($A2,Companies!$B$2:$B$1000,0)),""))} | G2: =IF($A2="","",IF($F2<>"",$F2+30,IF($D2<>"",$D2+30,""))) | K2: Month 1: Hi [Owner], [Your name] here - we spoke a while back about [Company]. No pitch, just keeping the door open: if you ever want to know what a shop like yours is going for right now, happy to share. Either way, keep crushing it.
B3: {=IF($A3="","",IFERROR(INDEX(Companies!$C$2:$C$1000,MATCH($A3,Companies!$B$2:$B$1000,0)),""))} | C3: {=IF($A3="","",IFERROR(INDEX(Companies!$D$2:$D$1000,MATCH($A3,Companies!$B$2:$B$1000,0)),""))} | G3: =IF($A3="","",IF($F3<>"",$F3+30,IF($D3<>"",$D3+30,""))) | K3: Month 2: Hi [Owner], [Your name] again. We just closed on another [trade] company in the area. If you're ever curious how [Company] stacks up value-wise, it's a 10-minute call. Zero pressure.
B4: {=IF($A4="","",IFERROR(INDEX(Companies!$C$2:$C$1000,MATCH($A4,Companies!$B$2:$B$1000,0)),""))} | C4: {=IF($A4="","",IFERROR(INDEX(Companies!$D$2:$D$1000,MATCH($A4,Companies!$B$2:$B$1000,0)),""))} | G4: =IF($A4="","",IF($F4<>"",$F4+30,IF($D4<>"",$D4+30,""))) | K4: Month 3: Hi [Owner] - most owners we sit down with wish they'd started the conversation two years before they wanted out. Even if selling is 5 years away for you, worth a coffee sometime?
B5: {=IF($A5="","",IFERROR(INDEX(Companies!$C$2:$C$1000,MATCH($A5,Companies!$B$2:$B$1000,0)),""))} | C5: {=IF($A5="","",IFERROR(INDEX(Companies!$D$2:$D$1000,MATCH($A5,Companies!$B$2:$B$1000,0)),""))} | G5: =IF($A5="","",IF($F5<>"",$F5+30,IF($D5<>"",$D5+30,""))) | K5: Month 4: Hi [Owner], still serious about buying [Company] whenever the timing is right for you. You know where to find me. - [Your name]
B6: {=IF($A6="","",IFERROR(INDEX(Companies!$C$2:$C$1000,MATCH($A6,Companies!$B$2:$B$1000,0)),""))} | C6: {=IF($A6="","",IFERROR(INDEX(Companies!$D$2:$D$1000,MATCH($A6,Companies!$B$2:$B$1000,0)),""))} | G6: =IF($A6="","",IF($F6<>"",$F6+30,IF($D6<>"",$D6+30,"")))
B7: {=IF($A7="","",IFERROR(INDEX(Companies!$C$2:$C$1000,MATCH($A7,Companies!$B$2:$B$1000,0)),""))} | C7: {=IF($A7="","",IFERROR(INDEX(Companies!$D$2:$D$1000,MATCH($A7,Companies!$B$2:$B$1000,0)),""))} | G7: =IF($A7="","",IF($F7<>"",$F7+30,IF($D7<>"",$D7+30,""))) | K7: THE RULES: If anyone replies STOP, 'don't text me', or anything like it - set Status to OPTED OUT immediately and never text again.
B8: {=IF($A8="","",IFERROR(INDEX(Companies!$C$2:$C$1000,MATCH($A8,Companies!$B$2:$B$1000,0)),""))} | C8: {=IF($A8="","",IFERROR(INDEX(Companies!$D$2:$D$1000,MATCH($A8,Companies!$B$2:$B$1000,0)),""))} | G8: =IF($A8="","",IF($F8<>"",$F8+30,IF($D8<>"",$D8+30,""))) | K8: Do NOT load these numbers into a mass-texting app. Nobody on this list opted in; blasting them is TCPA exposure at $500-$1,500 per text. Manual, personal, one at a time.
B9: {=IF($A9="","",IFERROR(INDEX(Companies!$C$2:$C$1000,MATCH($A9,Companies!$B$2:$B$1000,0)),""))} | C9: {=IF($A9="","",IFERROR(INDEX(Companies!$D$2:$D$1000,MATCH($A9,Companies!$B$2:$B$1000,0)),""))} | G9: =IF($A9="","",IF($F9<>"",$F9+30,IF($D9<>"",$D9+30,"")))
B10: {=IF($A10="","",IFERROR(INDEX(Companies!$C$2:$C$1000,MATCH($A10,Companies!$B$2:$B$1000,0)),""))} | C10: {=IF($A10="","",IFERROR(INDEX(Companies!$D$2:$D$1000,MATCH($A10,Companies!$B$2:$B$1000,0)),""))} | G10: =IF($A10="","",IF($F10<>"",$F10+30,IF($D10<>"",$D10+30,"")))
B11: {=IF($A11="","",IFERROR(INDEX(Companies!$C$2:$C$1000,MATCH($A11,Companies!$B$2:$B$1000,0)),""))} | C11: {=IF($A11="","",IFERROR(INDEX(Companies!$D$2:$D$1000,MATCH($A11,Companies!$B$2:$B$1000,0)),""))} | G11: =IF($A11="","",IF($F11<>"",$F11+30,IF($D11<>"",$D11+30,"")))
B12: {=IF($A12="","",IFERROR(INDEX(Companies!$C$2:$C$1000,MATCH($A12,Companies!$B$2:$B$1000,0)),""))} | C12: {=IF($A12="","",IFERROR(INDEX(Companies!$D$2:$D$1000,MATCH($A12,Companies!$B$2:$B$1000,0)),""))} | G12: =IF($A12="","",IF($F12<>"",$F12+30,IF($D12<>"",$D12+30,"")))
B13: {=IF($A13="","",IFERROR(INDEX(Companies!$C$2:$C$1000,MATCH($A13,Companies!$B$2:$B$1000,0)),""))} | C13: {=IF($A13="","",IFERROR(INDEX(Companies!$D$2:$D$1000,MATCH($A13,Companies!$B$2:$B$1000,0)),""))} | G13: =IF($A13="","",IF($F13<>"",$F13+30,IF($D13<>"",$D13+30,"")))
B14: {=IF($A14="","",IFERROR(INDEX(Companies!$C$2:$C$1000,MATCH($A14,Companies!$B$2:$B$1000,0)),""))} | C14: {=IF($A14="","",IFERROR(INDEX(Companies!$D$2:$D$1000,MATCH($A14,Companies!$B$2:$B$1000,0)),""))} | G14: =IF($A14="","",IF($F14<>"",$F14+30,IF($D14<>"",$D14+30,"")))
B15: {=IF($A15="","",IFERROR(INDEX(Companies!$C$2:$C$1000,MATCH($A15,Companies!$B$2:$B$1000,0)),""))} | C15: {=IF($A15="","",IFERROR(INDEX(Companies!$D$2:$D$1000,MATCH($A15,Companies!$B$2:$B$1000,0)),""))} | G15: =IF($A15="","",IF($F15<>"",$F15+30,IF($D15<>"",$D15+30,"")))
B16: {=IF($A16="","",IFERROR(INDEX(Companies!$C$2:$C$1000,MATCH($A16,Companies!$B$2:$B$1000,0)),""))} | C16: {=IF($A16="","",IFERROR(INDEX(Companies!$D$2:$D$1000,MATCH($A16,Companies!$B$2:$B$1000,0)),""))} | G16: =IF($A16="","",IF($F16<>"",$F16+30,IF($D16<>"",$D16+30,"")))
B17: {=IF($A17="","",IFERROR(INDEX(Companies!$C$2:$C$1000,MATCH($A17,Companies!$B$2:$B$1000,0)),""))} | C17: {=IF($A17="","",IFERROR(INDEX(Companies!$D$2:$D$1000,MATCH($A17,Companies!$B$2:$B$1000,0)),""))} | G17: =IF($A17="","",IF($F17<>"",$F17+30,IF($D17<>"",$D17+30,"")))
B18: {=IF($A18="","",IFERROR(INDEX(Companies!$C$2:$C$1000,MATCH($A18,Companies!$B$2:$B$1000,0)),""))} | C18: {=IF($A18="","",IFERROR(INDEX(Companies!$D$2:$D$1000,MATCH($A18,Companies!$B$2:$B$1000,0)),""))} | G18: =IF($A18="","",IF($F18<>"",$F18+30,IF($D18<>"",$D18+30,"")))
B19: {=IF($A19="","",IFERROR(INDEX(Companies!$C$2:$C$1000,MATCH($A19,Companies!$B$2:$B$1000,0)),""))} | C19: {=IF($A19="","",IFERROR(INDEX(Companies!$D$2:$D$1000,MATCH($A19,Companies!$B$2:$B$1000,0)),""))} | G19: =IF($A19="","",IF($F19<>"",$F19+30,IF($D19<>"",$D19+30,"")))
B20: {=IF($A20="","",IFERROR(INDEX(Companies!$C$2:$C$1000,MATCH($A20,Companies!$B$2:$B$1000,0)),""))} | C20: {=IF($A20="","",IFERROR(INDEX(Companies!$D$2:$D$1000,MATCH($A20,Companies!$B$2:$B$1000,0)),""))} | G20: =IF($A20="","",IF($F20<>"",$F20+30,IF($D20<>"",$D20+30,"")))
... B500: {=IF($A500="","",IFERROR(INDEX(Companies!$C$2:$C$1000,MATCH($A500,Companies!$B$2:$B$1000,0)),""))} | C500: {=IF($A500="","",IFERROR(INDEX(Companies!$D$2:$D$1000,MATCH($A500,Companies!$B$2:$B$1000,0)),""))} | G500: =IF($A500="","",IF($F500<>"",$F500+30,IF($D500<>"",$D500+30,"")))

Sheet Read Me
B2: HOW THIS SYSTEM WORKS - THE CALL -> ROUTE FLOW
B4: EVERY CALL ENDS IN ONE OF THREE ROUTES:
B5: GOOD CALL (meeting agreed): set Stage to '3. Meeting Set' on Companies, fill in Meeting Date + Meeting Time & Place. Outcome in Call Log = 'Meeting Set' (turns green).
B6: NO ANSWER / NOT YET: leave Stage at '2. In Call Rotation', set who dials next in 'Next Caller', log the attempt. A different rep takes the next dial.
B7: HARD NO: Outcome = 'Not Interested - move to SMS List'. Set Stage to 'X. SMS Nurture (Said No)', then go to the SMS Nurture tab and pick the company from the dropdown in column A - owner name and cell fill in automatically. Text them monthly from there. DO NOT keep dialing a hard no.
B9: THE ROTATION (5 callers, fresh voice each attempt):
B10: Before dialing, check 'Last Caller' and 'Calls This Wk' on Companies - both fill in automatically from the Call Log. If Last Caller was you, hand it to the rep in 'Next Caller'.
B11: Companies in rotation that nobody called this week turn ORANGE. The dashboard counts them - keep that number at zero.
B12: A word of caution from experience: rotating voices works for REACHING people who don't pick up. Re-dialing an owner who already said no - from 5 different people in one week - burns your name in a market where owners all know each other. Hard no = SMS list, not more dials.
B14: SMS NURTURE TAB:
B15: 'Next Text Due' auto-calculates 30 days after the last text (or the date added). Rows due turn YELLOW. Four rotating scripts are on the right side of that tab - personalize the brackets, send manually from your own phone, one at a time.
B16: If anyone replies STOP or asks you to quit texting: set Status to OPTED OUT (row turns red) and never contact again. Never load this list into a mass-texting platform - nobody on it opted in, and unsolicited automated texts run $500-$1,500 each in TCPA damages.
... B28: PIPELINE: 1 Not Contacted > 2 In Call Rotation > 3 Meeting Set > 4 Meeting Held > 5 NDA > 6 Financials > 7 LOI > 8 Diligence > 9 Closed. X = Said No (SMS nurture).
